<?xml version="1.0" encoding="UTF-8" standalone="yes"?>
<unit xmlns="http://www.sdml.info/srcML/src" language="Java"
      filename="D:\bio\git\biorimp\BIO-RIMP\test_data\code\guava\src\com\google\common\collect\GenericMapMaker.java">
    <comment type="block">/*
        * Copyright (C) 2010 The Guava Authors
        *
        * Licensed under the Apache License, Version 2.0 (the "License");
        * you may not use this file except in compliance with the License.
        * You may obtain a copy of the License at
        *
        * http://www.apache.org/licenses/LICENSE-2.0
        *
        * Unless required by applicable law or agreed to in writing, software
        * distributed under the License is distributed on an "AS-IS" BASIS,
        * WITHOUT WARRANTIES OR CONDITIONS OF ANY KIND, either express or implied.
        * See the License for the specific language governing permissions and
        * limitations under the License.
        */
    </comment>

    <package>package
        <name><name>com</name>.<name>google</name>.<name>common</name>.
            <name>collect</name>
        </name>
        ;
    </package>

    <import>import
        <name><name>com</name>.<name>google</name>.<name>common</name>.<name>annotations</name>.
            <name>Beta</name>
        </name>
        ;
    </import>
    <import>import
        <name><name>com</name>.<name>google</name>.<name>common</name>.<name>annotations</name>.
            <name>GwtCompatible</name>
        </name>
        ;
    </import>
    <import>import
        <name><name>com</name>.<name>google</name>.<name>common</name>.<name>annotations</name>.
            <name>GwtIncompatible</name>
        </name>
        ;
    </import>
    <import>import
        <name><name>com</name>.<name>google</name>.<name>common</name>.<name>base</name>.
            <name>Equivalence</name>
        </name>
        ;
    </import>
    <import>import
        <name><name>com</name>.<name>google</name>.<name>common</name>.<name>base</name>.
            <name>Function</name>
        </name>
        ;
    </import>
    <import>import
        <name><name>com</name>.<name>google</name>.<name>common</name>.<name>base</name>.
            <name>MoreObjects</name>
        </name>
        ;
    </import>
    <import>import
        <name><name>com</name>.<name>google</name>.<name>common</name>.<name>collect</name>.<name>MapMaker</name>.
            <name>RemovalListener</name>
        </name>
        ;
    </import>
    <import>import
        <name><name>com</name>.<name>google</name>.<name>common</name>.<name>collect</name>.<name>MapMaker</name>.
            <name>RemovalNotification</name>
        </name>
        ;
    </import>

    <import>import
        <name><name>java</name>.<name>util</name>.<name>concurrent</name>.
            <name>ConcurrentMap</name>
        </name>
        ;
    </import>
    <import>import
        <name><name>java</name>.<name>util</name>.<name>concurrent</name>.
            <name>TimeUnit</name>
        </name>
        ;
    </import>

    <comment type="javadoc">/**
        * A class exactly like {@link MapMaker}, except restricted in the types of maps it can build.
        * For the most part, you should probably just ignore the existence of this class.
        *
        * @param &lt;K0&gt; the base type for all key types of maps built by this map maker
        * @param &lt;V0&gt; the base type for all value types of maps built by this map maker
        * @author Kevin Bourrillion
        * @since 7.0
        * @deprecated This class existed only to support the generic paramterization necessary for the
        * caching functionality in {@code MapMaker}. That functionality has been moved to {@link
        * com.google.common.cache.CacheBuilder}, which is a properly generified class and thus needs no
        * "Generic" equivalent; simple use {@code CacheBuilder} naturally. For general migration
        * instructions, see the &lt;a
        * href="https://github.com/google/guava/wiki/MapMakerMigration"&gt;MapMaker Migration
        * Guide&lt;/a&gt;.
        */
    </comment>
    <class>
        <annotation>@
            <name>Beta</name>
        </annotation>
        <annotation>@
            <name>Deprecated</name>
        </annotation>
        <annotation>@
            <name>GwtCompatible</name>
            <argument_list>(emulated = true)</argument_list>
        </annotation>
        <specifier>abstract</specifier>
        class
        <name>
            <name>GenericMapMaker</name>
            <argument_list>&lt;
                <argument>
                    <name>K0</name>
                </argument>
                ,
                <argument>
                    <name>V0</name>
                </argument>
                &gt;
            </argument_list>
        </name>
        <block>{
            <enum>
                <annotation>@
                    <name>GwtIncompatible</name>
                    <argument_list>("To be supported")</argument_list>
                </annotation>
                enum <name>NullListener</name>
                <super>
                    <implements>implements
                        <name>
                            <name>RemovalListener</name>
                            <argument_list>&lt;
                                <argument>
                                    <name>Object</name>
                                </argument>
                                ,
                                <argument>
                                    <name>Object</name>
                                </argument>
                                &gt;
                            </argument_list>
                        </name>
                    </implements>
                </super>
                <block>{
                    <expr_stmt>
                        <expr>
                            <name>INSTANCE</name>
                        </expr>
                        ;
                    </expr_stmt>

                    <function>
                        <type>
                            <annotation>@
                                <name>Override</name>
                            </annotation>
                            <specifier>public</specifier>
                            <name>void</name>
                        </type>
                        <name>onRemoval</name>
                        <parameter_list>(
                            <param>
                                <decl>
                                    <type>
                                        <name>
                                            <name>RemovalNotification</name>
                                            <argument_list>&lt;
                                                <argument>
                                                    <name>Object</name>
                                                </argument>
                                                ,
                                                <argument>
                                                    <name>Object</name>
                                                </argument>
                                                &gt;
                                            </argument_list>
                                        </name>
                                    </type>
                                    <name>notification</name>
                                </decl>
                            </param>
                            )
                        </parameter_list>
                        <block>{}</block>
                    </function>
                    }
                </block>
            </enum>

            <comment type="line">// Set by MapMaker, but sits in this class to preserve the type relationship</comment>
            <decl_stmt>
                <decl>
                    <type>
                        <annotation>@
                            <name>GwtIncompatible</name>
                            <argument_list>("To be supported")</argument_list>
                        </annotation>
                        <name>
                            <name>RemovalListener</name>
                            <argument_list>&lt;
                                <argument>
                                    <name>K0</name>
                                </argument>
                                ,
                                <argument>
                                    <name>V0</name>
                                </argument>
                                &gt;
                            </argument_list>
                        </name>
                    </type>
                    <name>removalListener</name>
                </decl>
                ;
            </decl_stmt>

            <comment type="line">// No subclasses but our own</comment>
            <constructor>
                <name>GenericMapMaker</name>
                <parameter_list>()</parameter_list>
                <block>{}</block>
            </constructor>

            <comment type="javadoc">/**
                * See {@link MapMaker#keyEquivalence}.
                */
            </comment>
            <function_decl>
                <type>
                    <annotation>@
                        <name>GwtIncompatible</name>
                        <argument_list>("To be supported")</argument_list>
                    </annotation>
                    <specifier>abstract</specifier>
                    <name>
                        <name>GenericMapMaker</name>
                        <argument_list>&lt;
                            <argument>
                                <name>K0</name>
                            </argument>
                            ,
                            <argument>
                                <name>V0</name>
                            </argument>
                            &gt;
                        </argument_list>
                    </name>
                </type>
                <name>keyEquivalence</name>
                <parameter_list>(
                    <param>
                        <decl>
                            <type>
                                <name>
                                    <name>Equivalence</name>
                                    <argument_list>&lt;
                                        <argument>
                                            <name>Object</name>
                                        </argument>
                                        &gt;
                                    </argument_list>
                                </name>
                            </type>
                            <name>equivalence</name>
                        </decl>
                    </param>
                    )
                </parameter_list>
                ;
            </function_decl>

            <comment type="javadoc">/**
                * See {@link MapMaker#initialCapacity}.
                */
            </comment>
            <function_decl>
                <type>
                    <specifier>public</specifier>
                    <specifier>abstract</specifier>
                    <name>
                        <name>GenericMapMaker</name>
                        <argument_list>&lt;
                            <argument>
                                <name>K0</name>
                            </argument>
                            ,
                            <argument>
                                <name>V0</name>
                            </argument>
                            &gt;
                        </argument_list>
                    </name>
                </type>
                <name>initialCapacity</name>
                <parameter_list>(
                    <param>
                        <decl>
                            <type>
                                <name>int</name>
                            </type>
                            <name>initialCapacity</name>
                        </decl>
                    </param>
                    )
                </parameter_list>
                ;
            </function_decl>

            <comment type="javadoc">/**
                * See {@link MapMaker#maximumSize}.
                */
            </comment>
            <function_decl>
                <type>
                    <specifier>abstract</specifier>
                    <name>
                        <name>GenericMapMaker</name>
                        <argument_list>&lt;
                            <argument>
                                <name>K0</name>
                            </argument>
                            ,
                            <argument>
                                <name>V0</name>
                            </argument>
                            &gt;
                        </argument_list>
                    </name>
                </type>
                <name>maximumSize</name>
                <parameter_list>(
                    <param>
                        <decl>
                            <type>
                                <name>int</name>
                            </type>
                            <name>maximumSize</name>
                        </decl>
                    </param>
                    )
                </parameter_list>
                ;
            </function_decl>

            <comment type="javadoc">/**
                * See {@link MapMaker#concurrencyLevel}.
                */
            </comment>
            <function_decl>
                <type>
                    <specifier>public</specifier>
                    <specifier>abstract</specifier>
                    <name>
                        <name>GenericMapMaker</name>
                        <argument_list>&lt;
                            <argument>
                                <name>K0</name>
                            </argument>
                            ,
                            <argument>
                                <name>V0</name>
                            </argument>
                            &gt;
                        </argument_list>
                    </name>
                </type>
                <name>concurrencyLevel</name>
                <parameter_list>(
                    <param>
                        <decl>
                            <type>
                                <name>int</name>
                            </type>
                            <name>concurrencyLevel</name>
                        </decl>
                    </param>
                    )
                </parameter_list>
                ;
            </function_decl>

            <comment type="javadoc">/**
                * See {@link MapMaker#weakKeys}.
                */
            </comment>
            <function_decl>
                <type>
                    <annotation>@
                        <name>GwtIncompatible</name>
                        <argument_list>("java.lang.ref.WeakReference")</argument_list>
                    </annotation>
                    <specifier>public</specifier>
                    <specifier>abstract</specifier>
                    <name>
                        <name>GenericMapMaker</name>
                        <argument_list>&lt;
                            <argument>
                                <name>K0</name>
                            </argument>
                            ,
                            <argument>
                                <name>V0</name>
                            </argument>
                            &gt;
                        </argument_list>
                    </name>
                </type>
                <name>weakKeys</name>
                <parameter_list>()</parameter_list>;
            </function_decl>

            <comment type="javadoc">/**
                * See {@link MapMaker#weakValues}.
                */
            </comment>
            <function_decl>
                <type>
                    <annotation>@
                        <name>GwtIncompatible</name>
                        <argument_list>("java.lang.ref.WeakReference")</argument_list>
                    </annotation>
                    <specifier>public</specifier>
                    <specifier>abstract</specifier>
                    <name>
                        <name>GenericMapMaker</name>
                        <argument_list>&lt;
                            <argument>
                                <name>K0</name>
                            </argument>
                            ,
                            <argument>
                                <name>V0</name>
                            </argument>
                            &gt;
                        </argument_list>
                    </name>
                </type>
                <name>weakValues</name>
                <parameter_list>()</parameter_list>;
            </function_decl>

            <comment type="javadoc">/**
                * See {@link MapMaker#softValues}.
                *
                * @deprecated Caching functionality in {@code MapMaker} has been moved to {@link
                * com.google.common.cache.CacheBuilder}, with {@link #softValues} being replaced by {@link
                * com.google.common.cache.CacheBuilder#softValues}. Note that {@code CacheBuilder} is simply
                * an enhanced API for an implementation which was branched from {@code MapMaker}.
                */
            </comment>
            <function_decl>
                <type>
                    <annotation>@
                        <name>Deprecated</name>
                    </annotation>
                    <annotation>@
                        <name>GwtIncompatible</name>
                        <argument_list>("java.lang.ref.SoftReference")</argument_list>
                    </annotation>
                    <specifier>abstract</specifier>
                    <name>
                        <name>GenericMapMaker</name>
                        <argument_list>&lt;
                            <argument>
                                <name>K0</name>
                            </argument>
                            ,
                            <argument>
                                <name>V0</name>
                            </argument>
                            &gt;
                        </argument_list>
                    </name>
                </type>
                <name>softValues</name>
                <parameter_list>()</parameter_list>;
            </function_decl>

            <comment type="javadoc">/**
                * See {@link MapMaker#expireAfterWrite}.
                */
            </comment>
            <function_decl>
                <type>
                    <specifier>abstract</specifier>
                    <name>
                        <name>GenericMapMaker</name>
                        <argument_list>&lt;
                            <argument>
                                <name>K0</name>
                            </argument>
                            ,
                            <argument>
                                <name>V0</name>
                            </argument>
                            &gt;
                        </argument_list>
                    </name>
                </type>
                <name>expireAfterWrite</name>
                <parameter_list>(
                    <param>
                        <decl>
                            <type>
                                <name>long</name>
                            </type>
                            <name>duration</name>
                        </decl>
                    </param>
                    ,
                    <param>
                        <decl>
                            <type>
                                <name>TimeUnit</name>
                            </type>
                            <name>unit</name>
                        </decl>
                    </param>
                    )
                </parameter_list>
                ;
            </function_decl>

            <comment type="javadoc">/**
                * See {@link MapMaker#expireAfterAccess}.
                */
            </comment>
            <function_decl>
                <type>
                    <annotation>@
                        <name>GwtIncompatible</name>
                        <argument_list>("To be supported")</argument_list>
                    </annotation>
                    <specifier>abstract</specifier>
                    <name>
                        <name>GenericMapMaker</name>
                        <argument_list>&lt;
                            <argument>
                                <name>K0</name>
                            </argument>
                            ,
                            <argument>
                                <name>V0</name>
                            </argument>
                            &gt;
                        </argument_list>
                    </name>
                </type>
                <name>expireAfterAccess</name>
                <parameter_list>(
                    <param>
                        <decl>
                            <type>
                                <name>long</name>
                            </type>
                            <name>duration</name>
                        </decl>
                    </param>
                    ,
                    <param>
                        <decl>
                            <type>
                                <name>TimeUnit</name>
                            </type>
                            <name>unit</name>
                        </decl>
                    </param>
                    )
                </parameter_list>
                ;
            </function_decl>

            <comment type="block">/*
                * Note that MapMaker's removalListener() is not here, because once you're interacting with a
                * GenericMapMaker you've already called that, and shouldn't be calling it again.
                */
            </comment>

            <function>
                <type>
                    <annotation>@
                        <name>SuppressWarnings</name>
                        <argument_list>("unchecked")</argument_list>
                    </annotation>
                    <comment type="line">// safe covariant cast</comment>
                    <annotation>@
                        <name>GwtIncompatible</name>
                        <argument_list>("To be supported")</argument_list>
                    </annotation>
                    <argument_list>&lt;
                        <argument>
                            <name>K</name>
                            <extends>extends
                                <name>K0</name>
                            </extends>
                        </argument>
                        ,
                        <argument>
                            <name>V</name>
                            <extends>extends
                                <name>V0</name>
                            </extends>
                        </argument>
                        &gt;
                    </argument_list>
                    <name>
                        <name>RemovalListener</name>
                        <argument_list>&lt;
                            <argument>
                                <name>K</name>
                            </argument>
                            ,
                            <argument>
                                <name>V</name>
                            </argument>
                            &gt;
                        </argument_list>
                    </name>
                </type>
                <name>getRemovalListener</name>
                <parameter_list>()</parameter_list>
                <block>{
                    <return>return
                        <expr>(
                            <name>
                                <name>RemovalListener</name>
                                <argument_list>&lt;
                                    <argument>
                                        <name>K</name>
                                    </argument>
                                    ,
                                    <argument>
                                        <name>V</name>
                                    </argument>
                                    &gt;
                                </argument_list>
                            </name>
                            )
                            <call>
                                <name><name>MoreObjects</name>.
                                    <name>firstNonNull</name>
                                </name>
                                <argument_list>(
                                    <argument>
                                        <expr>
                                            <name>removalListener</name>
                                        </expr>
                                    </argument>
                                    ,
                                    <argument>
                                        <expr>
                                            <name><name>NullListener</name>.
                                                <name>INSTANCE</name>
                                            </name>
                                        </expr>
                                    </argument>
                                    )
                                </argument_list>
                            </call>
                        </expr>
                        ;
                    </return>
                    }
                </block>
            </function>

            <comment type="javadoc">/**
                * See {@link MapMaker#makeMap}.
                */
            </comment>
            <function_decl>
                <type>
                    <specifier>public</specifier>
                    <specifier>abstract</specifier>
                    <argument_list>&lt;
                        <argument>
                            <name>K</name>
                            <extends>extends
                                <name>K0</name>
                            </extends>
                        </argument>
                        ,
                        <argument>
                            <name>V</name>
                            <extends>extends
                                <name>V0</name>
                            </extends>
                        </argument>
                        &gt;
                    </argument_list>
                    <name>
                        <name>ConcurrentMap</name>
                        <argument_list>&lt;
                            <argument>
                                <name>K</name>
                            </argument>
                            ,
                            <argument>
                                <name>V</name>
                            </argument>
                            &gt;
                        </argument_list>
                    </name>
                </type>
                <name>makeMap</name>
                <parameter_list>()</parameter_list>;
            </function_decl>

            <comment type="javadoc">/**
                * See {@link MapMaker#makeCustomMap}.
                */
            </comment>
            <function_decl>
                <type>
                    <annotation>@
                        <name>GwtIncompatible</name>
                        <argument_list>("MapMakerInternalMap")</argument_list>
                    </annotation>
                    <specifier>abstract</specifier>
                    <argument_list>&lt;
                        <argument>
                            <name>K</name>
                        </argument>
                        ,
                        <argument>
                            <name>V</name>
                        </argument>
                        &gt;
                    </argument_list>
                    <name>
                        <name>MapMakerInternalMap</name>
                        <argument_list>&lt;
                            <argument>
                                <name>K</name>
                            </argument>
                            ,
                            <argument>
                                <name>V</name>
                            </argument>
                            &gt;
                        </argument_list>
                    </name>
                </type>
                <name>makeCustomMap</name>
                <parameter_list>()</parameter_list>;
            </function_decl>

            <comment type="javadoc">/**
                * See {@link MapMaker#makeComputingMap}.
                */
            </comment>
            <function_decl>
                <type>
                    <annotation>@
                        <name>Deprecated</name>
                    </annotation>
                    <specifier>abstract</specifier>
                    <argument_list>&lt;
                        <argument>
                            <name>K</name>
                            <extends>extends
                                <name>K0</name>
                            </extends>
                        </argument>
                        ,
                        <argument>
                            <name>V</name>
                            <extends>extends
                                <name>V0</name>
                            </extends>
                        </argument>
                        &gt;
                    </argument_list>
                    <name>
                        <name>ConcurrentMap</name>
                        <argument_list>&lt;
                            <argument>
                                <name>K</name>
                            </argument>
                            ,
                            <argument>
                                <name>V</name>
                            </argument>
                            &gt;
                        </argument_list>
                    </name>
                </type>
                <name>makeComputingMap</name>
                <parameter_list>(
                    <param>
                        <decl>
                            <type>
                                <name>
                                    <name>Function</name>
                                    <argument_list>&lt;
                                        <argument>
                                            <name>?</name>
                                            <super>super
                                                <name>K</name>
                                            </super>
                                        </argument>
                                        ,
                                        <argument>
                                            <name>?</name>
                                            <extends>extends
                                                <name>V</name>
                                            </extends>
                                        </argument>
                                        &gt;
                                    </argument_list>
                                </name>
                            </type>
                            <name>computingFunction</name>
                        </decl>
                    </param>
                    )
                </parameter_list>
                ;
            </function_decl>
            }
        </block>
    </class>
</unit>
