<?xml version="1.0" encoding="UTF-8" standalone="yes"?>
<unit xmlns="http://www.sdml.info/srcML/src" language="Java"
      filename="D:\bio\git\biorimp\BIO-RIMP\test_data\code\joda\src\main\java\org\joda\beans\impl\direct\DirectMetaProperty.java">
    <comment type="block">/*
        * Copyright 2001-2014 Stephen Colebourne
        *
        * Licensed under the Apache License, Version 2.0 (the "License");
        * you may not use this file except in compliance with the License.
        * You may obtain a copy of the License at
        *
        * http://www.apache.org/licenses/LICENSE-2.0
        *
        * Unless required by applicable law or agreed to in writing, software
        * distributed under the License is distributed on an "AS IS" BASIS,
        * WITHOUT WARRANTIES OR CONDITIONS OF ANY KIND, either express or implied.
        * See the License for the specific language governing permissions and
        * limitations under the License.
        */
    </comment>
    <package>package
        <name><name>org</name>.<name>joda</name>.<name>beans</name>.<name>impl</name>.
            <name>direct</name>
        </name>
        ;
    </package>

    <import>import
        <name><name>java</name>.<name>lang</name>.<name>annotation</name>.
            <name>Annotation</name>
        </name>
        ;
    </import>
    <import>import
        <name><name>java</name>.<name>lang</name>.<name>reflect</name>.
            <name>Field</name>
        </name>
        ;
    </import>
    <import>import
        <name><name>java</name>.<name>lang</name>.<name>reflect</name>.
            <name>Type</name>
        </name>
        ;
    </import>
    <import>import
        <name><name>java</name>.<name>util</name>.
            <name>Arrays</name>
        </name>
        ;
    </import>
    <import>import
        <name><name>java</name>.<name>util</name>.
            <name>Collections</name>
        </name>
        ;
    </import>
    <import>import
        <name><name>java</name>.<name>util</name>.
            <name>List</name>
        </name>
        ;
    </import>
    <import>import
        <name><name>java</name>.<name>util</name>.
            <name>NoSuchElementException</name>
        </name>
        ;
    </import>

    <import>import
        <name><name>org</name>.<name>joda</name>.<name>beans</name>.
            <name>Bean</name>
        </name>
        ;
    </import>
    <import>import
        <name><name>org</name>.<name>joda</name>.<name>beans</name>.
            <name>MetaBean</name>
        </name>
        ;
    </import>
    <import>import
        <name><name>org</name>.<name>joda</name>.<name>beans</name>.
            <name>PropertyStyle</name>
        </name>
        ;
    </import>
    <import>import
        <name><name>org</name>.<name>joda</name>.<name>beans</name>.<name>impl</name>.
            <name>BasicMetaProperty</name>
        </name>
        ;
    </import>

    <comment type="javadoc">/**
        * A meta-property implementation designed for use by the code generator.
        * &lt;p&gt;
        * This meta-property uses reflection to find the {@code Field} to obtain the annotations.
        *
        * @param &lt;P&gt; the type of the property content
        * @author Stephen Colebourne
        */
    </comment>
    <class>
        <specifier>public</specifier>
        <specifier>final</specifier> class
        <name>
            <name>DirectMetaProperty</name>
            <argument_list>&lt;
                <argument>
                    <name>P</name>
                </argument>
                &gt;
            </argument_list>
        </name>
        <super>
            <extends>extends
                <name>
                    <name>BasicMetaProperty</name>
                    <argument_list>&lt;
                        <argument>
                            <name>P</name>
                        </argument>
                        &gt;
                    </argument_list>
                </name>
            </extends>
        </super>
        <block>{

            <comment type="javadoc">/** The meta-bean. */</comment>
            <decl_stmt>
                <decl>
                    <type>
                        <specifier>private</specifier>
                        <specifier>final</specifier>
                        <name>MetaBean</name>
                    </type>
                    <name>metaBean</name>
                </decl>
                ;
            </decl_stmt>
            <comment type="javadoc">/** The property type. */</comment>
            <decl_stmt>
                <decl>
                    <type>
                        <specifier>private</specifier>
                        <specifier>final</specifier>
                        <name>
                            <name>Class</name>
                            <argument_list>&lt;
                                <argument>
                                    <name>P</name>
                                </argument>
                                &gt;
                            </argument_list>
                        </name>
                    </type>
                    <name>propertyType</name>
                </decl>
                ;
            </decl_stmt>
            <comment type="javadoc">/** The declaring type. */</comment>
            <decl_stmt>
                <decl>
                    <type>
                        <specifier>private</specifier>
                        <specifier>final</specifier>
                        <name>
                            <name>Class</name>
                            <argument_list>&lt;
                                <argument>
                                    <name>?</name>
                                </argument>
                                &gt;
                            </argument_list>
                        </name>
                    </type>
                    <name>declaringType</name>
                </decl>
                ;
            </decl_stmt>
            <comment type="javadoc">/** The field implementing the property. */</comment>
            <decl_stmt>
                <decl>
                    <type>
                        <specifier>private</specifier>
                        <specifier>final</specifier>
                        <name>Field</name>
                    </type>
                    <name>field</name>
                </decl>
                ;
            </decl_stmt>
            <comment type="javadoc">/** The style. */</comment>
            <decl_stmt>
                <decl>
                    <type>
                        <specifier>private</specifier>
                        <specifier>final</specifier>
                        <name>PropertyStyle</name>
                    </type>
                    <name>style</name>
                </decl>
                ;
            </decl_stmt>

            <comment type="javadoc">/**
                * Factory to create a read-write meta-property avoiding duplicate generics.
                *
                * @param &lt;P&gt; the property type
                * @param metaBean the meta-bean, not null
                * @param propertyName the property name, not empty
                * @param declaringType the type declaring the property, not null
                * @param propertyType the property type, not null
                * @return the property, not null
                */
            </comment>
            <function>
                <type>
                    <specifier>public</specifier>
                    <specifier>static</specifier>
                    <argument_list>&lt;
                        <argument>
                            <name>P</name>
                        </argument>
                        &gt;
                    </argument_list>
                    <name>
                        <name>DirectMetaProperty</name>
                        <argument_list>&lt;
                            <argument>
                                <name>P</name>
                            </argument>
                            &gt;
                        </argument_list>
                    </name>
                </type>
                <name>ofReadWrite</name>
                <parameter_list>(
                    <param>
                        <decl>
                            <type>
                                <name>MetaBean</name>
                            </type>
                            <name>metaBean</name>
                        </decl>
                    </param>
                    ,
                    <param>
                        <decl>
                            <type>
                                <name>String</name>
                            </type>
                            <name>propertyName</name>
                        </decl>
                    </param>
                    ,
                    <param>
                        <decl>
                            <type>
                                <name>
                                    <name>Class</name>
                                    <argument_list>&lt;
                                        <argument>
                                            <name>?</name>
                                        </argument>
                                        &gt;
                                    </argument_list>
                                </name>
                            </type>
                            <name>declaringType</name>
                        </decl>
                    </param>
                    ,
                    <param>
                        <decl>
                            <type>
                                <name>
                                    <name>Class</name>
                                    <argument_list>&lt;
                                        <argument>
                                            <name>P</name>
                                        </argument>
                                        &gt;
                                    </argument_list>
                                </name>
                            </type>
                            <name>propertyType</name>
                        </decl>
                    </param>
                    )
                </parameter_list>
                <block>{
                    <decl_stmt>
                        <decl>
                            <type>
                                <name>Field</name>
                            </type>
                            <name>field</name> =
                            <init>
                                <expr>
                                    <call>
                                        <name>findField</name>
                                        <argument_list>(
                                            <argument>
                                                <expr>
                                                    <name>metaBean</name>
                                                </expr>
                                            </argument>
                                            ,
                                            <argument>
                                                <expr>
                                                    <name>propertyName</name>
                                                </expr>
                                            </argument>
                                            )
                                        </argument_list>
                                    </call>
                                </expr>
                            </init>
                        </decl>
                        ;
                    </decl_stmt>
                    <return>return
                        <expr>new
                            <call>
                                <name>
                                    <name>DirectMetaProperty</name>
                                    <argument_list>&lt;
                                        <argument>
                                            <name>P</name>
                                        </argument>
                                        &gt;
                                    </argument_list>
                                </name>
                                <argument_list>(
                                    <argument>
                                        <expr>
                                            <name>metaBean</name>
                                        </expr>
                                    </argument>
                                    ,
                                    <argument>
                                        <expr>
                                            <name>propertyName</name>
                                        </expr>
                                    </argument>
                                    ,
                                    <argument>
                                        <expr>
                                            <name>declaringType</name>
                                        </expr>
                                    </argument>
                                    ,
                                    <argument>
                                        <expr>
                                            <name>propertyType</name>
                                        </expr>
                                    </argument>
                                    ,
                                    <argument>
                                        <expr>
                                            <name><name>PropertyStyle</name>.
                                                <name>READ_WRITE</name>
                                            </name>
                                        </expr>
                                    </argument>
                                    ,
                                    <argument>
                                        <expr>
                                            <name>field</name>
                                        </expr>
                                    </argument>
                                    )
                                </argument_list>
                            </call>
                        </expr>
                        ;
                    </return>
                    }
                </block>
            </function>

            <comment type="javadoc">/**
                * Factory to create a read-only meta-property avoiding duplicate generics.
                *
                * @param &lt;P&gt; the property type
                * @param metaBean the meta-bean, not null
                * @param propertyName the property name, not empty
                * @param declaringType the type declaring the property, not null
                * @param propertyType the property type, not null
                * @return the property, not null
                */
            </comment>
            <function>
                <type>
                    <specifier>public</specifier>
                    <specifier>static</specifier>
                    <argument_list>&lt;
                        <argument>
                            <name>P</name>
                        </argument>
                        &gt;
                    </argument_list>
                    <name>
                        <name>DirectMetaProperty</name>
                        <argument_list>&lt;
                            <argument>
                                <name>P</name>
                            </argument>
                            &gt;
                        </argument_list>
                    </name>
                </type>
                <name>ofReadOnly</name>
                <parameter_list>(
                    <param>
                        <decl>
                            <type>
                                <name>MetaBean</name>
                            </type>
                            <name>metaBean</name>
                        </decl>
                    </param>
                    ,
                    <param>
                        <decl>
                            <type>
                                <name>String</name>
                            </type>
                            <name>propertyName</name>
                        </decl>
                    </param>
                    ,
                    <param>
                        <decl>
                            <type>
                                <name>
                                    <name>Class</name>
                                    <argument_list>&lt;
                                        <argument>
                                            <name>?</name>
                                        </argument>
                                        &gt;
                                    </argument_list>
                                </name>
                            </type>
                            <name>declaringType</name>
                        </decl>
                    </param>
                    ,
                    <param>
                        <decl>
                            <type>
                                <name>
                                    <name>Class</name>
                                    <argument_list>&lt;
                                        <argument>
                                            <name>P</name>
                                        </argument>
                                        &gt;
                                    </argument_list>
                                </name>
                            </type>
                            <name>propertyType</name>
                        </decl>
                    </param>
                    )
                </parameter_list>
                <block>{
                    <decl_stmt>
                        <decl>
                            <type>
                                <name>Field</name>
                            </type>
                            <name>field</name> =
                            <init>
                                <expr>
                                    <call>
                                        <name>findField</name>
                                        <argument_list>(
                                            <argument>
                                                <expr>
                                                    <name>metaBean</name>
                                                </expr>
                                            </argument>
                                            ,
                                            <argument>
                                                <expr>
                                                    <name>propertyName</name>
                                                </expr>
                                            </argument>
                                            )
                                        </argument_list>
                                    </call>
                                </expr>
                            </init>
                        </decl>
                        ;
                    </decl_stmt>
                    <return>return
                        <expr>new
                            <call>
                                <name>
                                    <name>DirectMetaProperty</name>
                                    <argument_list>&lt;
                                        <argument>
                                            <name>P</name>
                                        </argument>
                                        &gt;
                                    </argument_list>
                                </name>
                                <argument_list>(
                                    <argument>
                                        <expr>
                                            <name>metaBean</name>
                                        </expr>
                                    </argument>
                                    ,
                                    <argument>
                                        <expr>
                                            <name>propertyName</name>
                                        </expr>
                                    </argument>
                                    ,
                                    <argument>
                                        <expr>
                                            <name>declaringType</name>
                                        </expr>
                                    </argument>
                                    ,
                                    <argument>
                                        <expr>
                                            <name>propertyType</name>
                                        </expr>
                                    </argument>
                                    ,
                                    <argument>
                                        <expr>
                                            <name><name>PropertyStyle</name>.
                                                <name>READ_ONLY</name>
                                            </name>
                                        </expr>
                                    </argument>
                                    ,
                                    <argument>
                                        <expr>
                                            <name>field</name>
                                        </expr>
                                    </argument>
                                    )
                                </argument_list>
                            </call>
                        </expr>
                        ;
                    </return>
                    }
                </block>
            </function>

            <comment type="javadoc">/**
                * Factory to create a write-only meta-property avoiding duplicate generics.
                *
                * @param &lt;P&gt; the property type
                * @param metaBean the meta-bean, not null
                * @param propertyName the property name, not empty
                * @param declaringType the type declaring the property, not null
                * @param propertyType the property type, not null
                * @return the property, not null
                */
            </comment>
            <function>
                <type>
                    <specifier>public</specifier>
                    <specifier>static</specifier>
                    <argument_list>&lt;
                        <argument>
                            <name>P</name>
                        </argument>
                        &gt;
                    </argument_list>
                    <name>
                        <name>DirectMetaProperty</name>
                        <argument_list>&lt;
                            <argument>
                                <name>P</name>
                            </argument>
                            &gt;
                        </argument_list>
                    </name>
                </type>
                <name>ofWriteOnly</name>
                <parameter_list>(
                    <param>
                        <decl>
                            <type>
                                <name>MetaBean</name>
                            </type>
                            <name>metaBean</name>
                        </decl>
                    </param>
                    ,
                    <param>
                        <decl>
                            <type>
                                <name>String</name>
                            </type>
                            <name>propertyName</name>
                        </decl>
                    </param>
                    ,
                    <param>
                        <decl>
                            <type>
                                <name>
                                    <name>Class</name>
                                    <argument_list>&lt;
                                        <argument>
                                            <name>?</name>
                                        </argument>
                                        &gt;
                                    </argument_list>
                                </name>
                            </type>
                            <name>declaringType</name>
                        </decl>
                    </param>
                    ,
                    <param>
                        <decl>
                            <type>
                                <name>
                                    <name>Class</name>
                                    <argument_list>&lt;
                                        <argument>
                                            <name>P</name>
                                        </argument>
                                        &gt;
                                    </argument_list>
                                </name>
                            </type>
                            <name>propertyType</name>
                        </decl>
                    </param>
                    )
                </parameter_list>
                <block>{
                    <decl_stmt>
                        <decl>
                            <type>
                                <name>Field</name>
                            </type>
                            <name>field</name> =
                            <init>
                                <expr>
                                    <call>
                                        <name>findField</name>
                                        <argument_list>(
                                            <argument>
                                                <expr>
                                                    <name>metaBean</name>
                                                </expr>
                                            </argument>
                                            ,
                                            <argument>
                                                <expr>
                                                    <name>propertyName</name>
                                                </expr>
                                            </argument>
                                            )
                                        </argument_list>
                                    </call>
                                </expr>
                            </init>
                        </decl>
                        ;
                    </decl_stmt>
                    <return>return
                        <expr>new
                            <call>
                                <name>
                                    <name>DirectMetaProperty</name>
                                    <argument_list>&lt;
                                        <argument>
                                            <name>P</name>
                                        </argument>
                                        &gt;
                                    </argument_list>
                                </name>
                                <argument_list>(
                                    <argument>
                                        <expr>
                                            <name>metaBean</name>
                                        </expr>
                                    </argument>
                                    ,
                                    <argument>
                                        <expr>
                                            <name>propertyName</name>
                                        </expr>
                                    </argument>
                                    ,
                                    <argument>
                                        <expr>
                                            <name>declaringType</name>
                                        </expr>
                                    </argument>
                                    ,
                                    <argument>
                                        <expr>
                                            <name>propertyType</name>
                                        </expr>
                                    </argument>
                                    ,
                                    <argument>
                                        <expr>
                                            <name><name>PropertyStyle</name>.
                                                <name>WRITE_ONLY</name>
                                            </name>
                                        </expr>
                                    </argument>
                                    ,
                                    <argument>
                                        <expr>
                                            <name>field</name>
                                        </expr>
                                    </argument>
                                    )
                                </argument_list>
                            </call>
                        </expr>
                        ;
                    </return>
                    }
                </block>
            </function>

            <comment type="javadoc">/**
                * Factory to create a buildable read-only meta-property avoiding duplicate generics.
                *
                * @param &lt;P&gt; the property type
                * @param metaBean the meta-bean, not null
                * @param propertyName the property name, not empty
                * @param declaringType the type declaring the property, not null
                * @param propertyType the property type, not null
                * @return the property, not null
                */
            </comment>
            <function>
                <type>
                    <specifier>public</specifier>
                    <specifier>static</specifier>
                    <argument_list>&lt;
                        <argument>
                            <name>P</name>
                        </argument>
                        &gt;
                    </argument_list>
                    <name>
                        <name>DirectMetaProperty</name>
                        <argument_list>&lt;
                            <argument>
                                <name>P</name>
                            </argument>
                            &gt;
                        </argument_list>
                    </name>
                </type>
                <name>ofReadOnlyBuildable</name>
                <parameter_list>(
                    <param>
                        <decl>
                            <type>
                                <name>MetaBean</name>
                            </type>
                            <name>metaBean</name>
                        </decl>
                    </param>
                    ,
                    <param>
                        <decl>
                            <type>
                                <name>String</name>
                            </type>
                            <name>propertyName</name>
                        </decl>
                    </param>
                    ,
                    <param>
                        <decl>
                            <type>
                                <name>
                                    <name>Class</name>
                                    <argument_list>&lt;
                                        <argument>
                                            <name>?</name>
                                        </argument>
                                        &gt;
                                    </argument_list>
                                </name>
                            </type>
                            <name>declaringType</name>
                        </decl>
                    </param>
                    ,
                    <param>
                        <decl>
                            <type>
                                <name>
                                    <name>Class</name>
                                    <argument_list>&lt;
                                        <argument>
                                            <name>P</name>
                                        </argument>
                                        &gt;
                                    </argument_list>
                                </name>
                            </type>
                            <name>propertyType</name>
                        </decl>
                    </param>
                    )
                </parameter_list>
                <block>{
                    <decl_stmt>
                        <decl>
                            <type>
                                <name>Field</name>
                            </type>
                            <name>field</name> =
                            <init>
                                <expr>
                                    <call>
                                        <name>findField</name>
                                        <argument_list>(
                                            <argument>
                                                <expr>
                                                    <name>metaBean</name>
                                                </expr>
                                            </argument>
                                            ,
                                            <argument>
                                                <expr>
                                                    <name>propertyName</name>
                                                </expr>
                                            </argument>
                                            )
                                        </argument_list>
                                    </call>
                                </expr>
                            </init>
                        </decl>
                        ;
                    </decl_stmt>
                    <return>return
                        <expr>new
                            <call>
                                <name>
                                    <name>DirectMetaProperty</name>
                                    <argument_list>&lt;
                                        <argument>
                                            <name>P</name>
                                        </argument>
                                        &gt;
                                    </argument_list>
                                </name>
                                <argument_list>(
                                    <argument>
                                        <expr>
                                            <name>metaBean</name>
                                        </expr>
                                    </argument>
                                    ,
                                    <argument>
                                        <expr>
                                            <name>propertyName</name>
                                        </expr>
                                    </argument>
                                    ,
                                    <argument>
                                        <expr>
                                            <name>declaringType</name>
                                        </expr>
                                    </argument>
                                    ,
                                    <argument>
                                        <expr>
                                            <name>propertyType</name>
                                        </expr>
                                    </argument>
                                    ,
                                    <argument>
                                        <expr>
                                            <name><name>PropertyStyle</name>.
                                                <name>READ_ONLY_BUILDABLE</name>
                                            </name>
                                        </expr>
                                    </argument>
                                    ,
                                    <argument>
                                        <expr>
                                            <name>field</name>
                                        </expr>
                                    </argument>
                                    )
                                </argument_list>
                            </call>
                        </expr>
                        ;
                    </return>
                    }
                </block>
            </function>

            <comment type="javadoc">/**
                * Factory to create a derived read-only meta-property avoiding duplicate generics.
                *
                * @param &lt;P&gt; the property type
                * @param metaBean the meta-bean, not null
                * @param propertyName the property name, not empty
                * @param declaringType the type declaring the property, not null
                * @param propertyType the property type, not null
                * @return the property, not null
                */
            </comment>
            <function>
                <type>
                    <specifier>public</specifier>
                    <specifier>static</specifier>
                    <argument_list>&lt;
                        <argument>
                            <name>P</name>
                        </argument>
                        &gt;
                    </argument_list>
                    <name>
                        <name>DirectMetaProperty</name>
                        <argument_list>&lt;
                            <argument>
                                <name>P</name>
                            </argument>
                            &gt;
                        </argument_list>
                    </name>
                </type>
                <name>ofDerived</name>
                <parameter_list>(
                    <param>
                        <decl>
                            <type>
                                <name>MetaBean</name>
                            </type>
                            <name>metaBean</name>
                        </decl>
                    </param>
                    ,
                    <param>
                        <decl>
                            <type>
                                <name>String</name>
                            </type>
                            <name>propertyName</name>
                        </decl>
                    </param>
                    ,
                    <param>
                        <decl>
                            <type>
                                <name>
                                    <name>Class</name>
                                    <argument_list>&lt;
                                        <argument>
                                            <name>?</name>
                                        </argument>
                                        &gt;
                                    </argument_list>
                                </name>
                            </type>
                            <name>declaringType</name>
                        </decl>
                    </param>
                    ,
                    <param>
                        <decl>
                            <type>
                                <name>
                                    <name>Class</name>
                                    <argument_list>&lt;
                                        <argument>
                                            <name>P</name>
                                        </argument>
                                        &gt;
                                    </argument_list>
                                </name>
                            </type>
                            <name>propertyType</name>
                        </decl>
                    </param>
                    )
                </parameter_list>
                <block>{
                    <decl_stmt>
                        <decl>
                            <type>
                                <name>Field</name>
                            </type>
                            <name>field</name> =
                            <init>
                                <expr>
                                    <call>
                                        <name>findField</name>
                                        <argument_list>(
                                            <argument>
                                                <expr>
                                                    <name>metaBean</name>
                                                </expr>
                                            </argument>
                                            ,
                                            <argument>
                                                <expr>
                                                    <name>propertyName</name>
                                                </expr>
                                            </argument>
                                            )
                                        </argument_list>
                                    </call>
                                </expr>
                            </init>
                        </decl>
                        ;
                    </decl_stmt>
                    <return>return
                        <expr>new
                            <call>
                                <name>
                                    <name>DirectMetaProperty</name>
                                    <argument_list>&lt;
                                        <argument>
                                            <name>P</name>
                                        </argument>
                                        &gt;
                                    </argument_list>
                                </name>
                                <argument_list>(
                                    <argument>
                                        <expr>
                                            <name>metaBean</name>
                                        </expr>
                                    </argument>
                                    ,
                                    <argument>
                                        <expr>
                                            <name>propertyName</name>
                                        </expr>
                                    </argument>
                                    ,
                                    <argument>
                                        <expr>
                                            <name>declaringType</name>
                                        </expr>
                                    </argument>
                                    ,
                                    <argument>
                                        <expr>
                                            <name>propertyType</name>
                                        </expr>
                                    </argument>
                                    ,
                                    <argument>
                                        <expr>
                                            <name><name>PropertyStyle</name>.
                                                <name>DERIVED</name>
                                            </name>
                                        </expr>
                                    </argument>
                                    ,
                                    <argument>
                                        <expr>
                                            <name>field</name>
                                        </expr>
                                    </argument>
                                    )
                                </argument_list>
                            </call>
                        </expr>
                        ;
                    </return>
                    }
                </block>
            </function>

            <comment type="javadoc">/**
                * Factory to create an imutable meta-property avoiding duplicate generics.
                *
                * @param &lt;P&gt; the property type
                * @param metaBean the meta-bean, not null
                * @param propertyName the property name, not empty
                * @param declaringType the type declaring the property, not null
                * @param propertyType the property type, not null
                * @return the property, not null
                */
            </comment>
            <function>
                <type>
                    <specifier>public</specifier>
                    <specifier>static</specifier>
                    <argument_list>&lt;
                        <argument>
                            <name>P</name>
                        </argument>
                        &gt;
                    </argument_list>
                    <name>
                        <name>DirectMetaProperty</name>
                        <argument_list>&lt;
                            <argument>
                                <name>P</name>
                            </argument>
                            &gt;
                        </argument_list>
                    </name>
                </type>
                <name>ofImmutable</name>
                <parameter_list>(
                    <param>
                        <decl>
                            <type>
                                <name>MetaBean</name>
                            </type>
                            <name>metaBean</name>
                        </decl>
                    </param>
                    ,
                    <param>
                        <decl>
                            <type>
                                <name>String</name>
                            </type>
                            <name>propertyName</name>
                        </decl>
                    </param>
                    ,
                    <param>
                        <decl>
                            <type>
                                <name>
                                    <name>Class</name>
                                    <argument_list>&lt;
                                        <argument>
                                            <name>?</name>
                                        </argument>
                                        &gt;
                                    </argument_list>
                                </name>
                            </type>
                            <name>declaringType</name>
                        </decl>
                    </param>
                    ,
                    <param>
                        <decl>
                            <type>
                                <name>
                                    <name>Class</name>
                                    <argument_list>&lt;
                                        <argument>
                                            <name>P</name>
                                        </argument>
                                        &gt;
                                    </argument_list>
                                </name>
                            </type>
                            <name>propertyType</name>
                        </decl>
                    </param>
                    )
                </parameter_list>
                <block>{
                    <decl_stmt>
                        <decl>
                            <type>
                                <name>Field</name>
                            </type>
                            <name>field</name> =
                            <init>
                                <expr>
                                    <call>
                                        <name>findField</name>
                                        <argument_list>(
                                            <argument>
                                                <expr>
                                                    <name>metaBean</name>
                                                </expr>
                                            </argument>
                                            ,
                                            <argument>
                                                <expr>
                                                    <name>propertyName</name>
                                                </expr>
                                            </argument>
                                            )
                                        </argument_list>
                                    </call>
                                </expr>
                            </init>
                        </decl>
                        ;
                    </decl_stmt>
                    <return>return
                        <expr>new
                            <call>
                                <name>
                                    <name>DirectMetaProperty</name>
                                    <argument_list>&lt;
                                        <argument>
                                            <name>P</name>
                                        </argument>
                                        &gt;
                                    </argument_list>
                                </name>
                                <argument_list>(
                                    <argument>
                                        <expr>
                                            <name>metaBean</name>
                                        </expr>
                                    </argument>
                                    ,
                                    <argument>
                                        <expr>
                                            <name>propertyName</name>
                                        </expr>
                                    </argument>
                                    ,
                                    <argument>
                                        <expr>
                                            <name>declaringType</name>
                                        </expr>
                                    </argument>
                                    ,
                                    <argument>
                                        <expr>
                                            <name>propertyType</name>
                                        </expr>
                                    </argument>
                                    ,
                                    <argument>
                                        <expr>
                                            <name><name>PropertyStyle</name>.
                                                <name>IMMUTABLE</name>
                                            </name>
                                        </expr>
                                    </argument>
                                    ,
                                    <argument>
                                        <expr>
                                            <name>field</name>
                                        </expr>
                                    </argument>
                                    )
                                </argument_list>
                            </call>
                        </expr>
                        ;
                    </return>
                    }
                </block>
            </function>

            <function>
                <type>
                    <specifier>private</specifier>
                    <specifier>static</specifier>
                    <name>Field</name>
                </type>
                <name>findField</name>
                <parameter_list>(
                    <param>
                        <decl>
                            <type>
                                <name>MetaBean</name>
                            </type>
                            <name>metaBean</name>
                        </decl>
                    </param>
                    ,
                    <param>
                        <decl>
                            <type>
                                <name>String</name>
                            </type>
                            <name>propertyName</name>
                        </decl>
                    </param>
                    )
                </parameter_list>
                <block>{
                    <decl_stmt>
                        <decl>
                            <type>
                                <name>Field</name>
                            </type>
                            <name>field</name> =
                            <init>
                                <expr>
                                    <name>null</name>
                                </expr>
                            </init>
                        </decl>
                        ;
                    </decl_stmt>
                    <decl_stmt>
                        <decl>
                            <type>
                                <name>
                                    <name>Class</name>
                                    <argument_list>&lt;
                                        <argument>
                                            <name>?</name>
                                        </argument>
                                        &gt;
                                    </argument_list>
                                </name>
                            </type>
                            <name>cls</name> =
                            <init>
                                <expr>
                                    <call>
                                        <name><name>metaBean</name>.
                                            <name>beanType</name>
                                        </name>
                                        <argument_list>()</argument_list>
                                    </call>
                                </expr>
                            </init>
                        </decl>
                        ;
                    </decl_stmt>
                    <while>while
                        <condition>(
                            <expr>
                                <name>cls</name>
                                !=
                                <name><name>DirectBean</name>.
                                    <name>
                                        <name/>
                                    </name>
                                </name>
                                class &amp;&amp; <name>cls</name> !=
                                <name><name>Object</name>.
                                    <name>
                                        <name/>
                                    </name>
                                </name>
                                class &amp;&amp; <name>cls</name> !=
                                <name>null</name>
                            </expr>
                            )
                        </condition>
                        <block>{
                            <try>try
                                <block>{
                                    <expr_stmt>
                                        <expr>
                                            <name>field</name>
                                            =
                                            <call>
                                                <name><name>cls</name>.
                                                    <name>getDeclaredField</name>
                                                </name>
                                                <argument_list>(
                                                    <argument>
                                                        <expr>
                                                            <name>propertyName</name>
                                                        </expr>
                                                    </argument>
                                                    )
                                                </argument_list>
                                            </call>
                                        </expr>
                                        ;
                                    </expr_stmt>
                                    <break>break;</break>
                                    }
                                </block>
                                <catch>catch (
                                    <param>
                                        <decl>
                                            <type>
                                                <name>NoSuchFieldException</name>
                                            </type>
                                            <name>ex</name>
                                        </decl>
                                    </param>
                                    )
                                    <block>{
                                        <try>try
                                            <block>{
                                                <expr_stmt>
                                                    <expr>
                                                        <name>field</name>
                                                        =
                                                        <call>
                                                            <name><name>cls</name>.
                                                                <name>getDeclaredField</name>
                                                            </name>
                                                            <argument_list>(
                                                                <argument>
                                                                    <expr>"_" +
                                                                        <name>propertyName</name>
                                                                    </expr>
                                                                </argument>
                                                                )
                                                            </argument_list>
                                                        </call>
                                                    </expr>
                                                    ;
                                                </expr_stmt>
                                                <break>break;</break>
                                                }
                                            </block>
                                            <catch>catch (
                                                <param>
                                                    <decl>
                                                        <type>
                                                            <name>NoSuchFieldException</name>
                                                        </type>
                                                        <name>ex2</name>
                                                    </decl>
                                                </param>
                                                )
                                                <block>{
                                                    <expr_stmt>
                                                        <expr>
                                                            <name>cls</name>
                                                            =
                                                            <call>
                                                                <name><name>cls</name>.
                                                                    <name>getSuperclass</name>
                                                                </name>
                                                                <argument_list>()</argument_list>
                                                            </call>
                                                        </expr>
                                                        ;
                                                    </expr_stmt>
                                                    }
                                                </block>
                                            </catch>
                                        </try>
                                        }
                                    </block>
                                </catch>
                            </try>
                            }
                        </block>
                    </while>
                    <return>return
                        <expr>
                            <name>field</name>
                        </expr>
                        ;
                    </return>
                    }
                </block>
            </function>

            <comment type="javadoc">/**
                * Constructor.
                *
                * @param metaBean the meta-bean, not null
                * @param propertyName the property name, not empty
                * @param declaringType the declaring type, not null
                * @param propertyType the property type, not null
                * @param style the style, not null
                * @param field the reflected field, not null
                */
            </comment>
            <constructor>
                <specifier>private</specifier>
                <name>DirectMetaProperty</name>
                <parameter_list>(
                    <param>
                        <decl>
                            <type>
                                <name>MetaBean</name>
                            </type>
                            <name>metaBean</name>
                        </decl>
                    </param>
                    ,
                    <param>
                        <decl>
                            <type>
                                <name>String</name>
                            </type>
                            <name>propertyName</name>
                        </decl>
                    </param>
                    ,
                    <param>
                        <decl>
                            <type>
                                <name>
                                    <name>Class</name>
                                    <argument_list>&lt;
                                        <argument>
                                            <name>?</name>
                                        </argument>
                                        &gt;
                                    </argument_list>
                                </name>
                            </type>
                            <name>declaringType</name>
                        </decl>
                    </param>
                    ,
                    <param>
                        <decl>
                            <type>
                                <name>
                                    <name>Class</name>
                                    <argument_list>&lt;
                                        <argument>
                                            <name>P</name>
                                        </argument>
                                        &gt;
                                    </argument_list>
                                </name>
                            </type>
                            <name>propertyType</name>
                        </decl>
                    </param>
                    ,
                    <param>
                        <decl>
                            <type>
                                <name>PropertyStyle</name>
                            </type>
                            <name>style</name>
                        </decl>
                    </param>
                    ,
                    <param>
                        <decl>
                            <type>
                                <name>Field</name>
                            </type>
                            <name>field</name>
                        </decl>
                    </param>
                    )
                </parameter_list>
                <block>{
                    <expr_stmt>
                        <expr>
                            <call>
                                <name>super</name>
                                <argument_list>(
                                    <argument>
                                        <expr>
                                            <name>propertyName</name>
                                        </expr>
                                    </argument>
                                    )
                                </argument_list>
                            </call>
                        </expr>
                        ;
                    </expr_stmt>
                    <if>if
                        <condition>(
                            <expr>
                                <name>metaBean</name>
                                ==
                                <name>null</name>
                            </expr>
                            )
                        </condition>
                        <then>
                            <block>{
                                <throw>throw
                                    <expr>new
                                        <call>
                                            <name>NullPointerException</name>
                                            <argument_list>(
                                                <argument>
                                                    <expr>"MetaBean must not be null"</expr>
                                                </argument>
                                                )
                                            </argument_list>
                                        </call>
                                    </expr>
                                    ;
                                </throw>
                                }
                            </block>
                        </then>
                    </if>
                    <if>if
                        <condition>(
                            <expr>
                                <name>declaringType</name>
                                ==
                                <name>null</name>
                            </expr>
                            )
                        </condition>
                        <then>
                            <block>{
                                <throw>throw
                                    <expr>new
                                        <call>
                                            <name>NullPointerException</name>
                                            <argument_list>(
                                                <argument>
                                                    <expr>"Declaring type must not be null"</expr>
                                                </argument>
                                                )
                                            </argument_list>
                                        </call>
                                    </expr>
                                    ;
                                </throw>
                                }
                            </block>
                        </then>
                    </if>
                    <if>if
                        <condition>(
                            <expr>
                                <name>propertyType</name>
                                ==
                                <name>null</name>
                            </expr>
                            )
                        </condition>
                        <then>
                            <block>{
                                <throw>throw
                                    <expr>new
                                        <call>
                                            <name>NullPointerException</name>
                                            <argument_list>(
                                                <argument>
                                                    <expr>"Property type must not be null"</expr>
                                                </argument>
                                                )
                                            </argument_list>
                                        </call>
                                    </expr>
                                    ;
                                </throw>
                                }
                            </block>
                        </then>
                    </if>
                    <if>if
                        <condition>(
                            <expr>
                                <name>style</name>
                                ==
                                <name>null</name>
                            </expr>
                            )
                        </condition>
                        <then>
                            <block>{
                                <throw>throw
                                    <expr>new
                                        <call>
                                            <name>NullPointerException</name>
                                            <argument_list>(
                                                <argument>
                                                    <expr>"PropertyStyle must not be null"</expr>
                                                </argument>
                                                )
                                            </argument_list>
                                        </call>
                                    </expr>
                                    ;
                                </throw>
                                }
                            </block>
                        </then>
                    </if>
                    <expr_stmt>
                        <expr>
                            <name><name>this</name>.
                                <name>metaBean</name>
                            </name>
                            =
                            <name>metaBean</name>
                        </expr>
                        ;
                    </expr_stmt>
                    <expr_stmt>
                        <expr>
                            <name><name>this</name>.
                                <name>propertyType</name>
                            </name>
                            =
                            <name>propertyType</name>
                        </expr>
                        ;
                    </expr_stmt>
                    <expr_stmt>
                        <expr>
                            <name><name>this</name>.
                                <name>declaringType</name>
                            </name>
                            =
                            <name>declaringType</name>
                        </expr>
                        ;
                    </expr_stmt>
                    <expr_stmt>
                        <expr>
                            <name><name>this</name>.
                                <name>style</name>
                            </name>
                            =
                            <name>style</name>
                        </expr>
                        ;
                    </expr_stmt>
                    <expr_stmt>
                        <expr>
                            <name><name>this</name>.
                                <name>field</name>
                            </name>
                            =
                            <name>field</name>
                        </expr>
                        ;
                    </expr_stmt>
                    <comment type="line">// may be null</comment>
                    }
                </block>
            </constructor>

            <comment type="line">//-----------------------------------------------------------------------</comment>
            <function>
                <type>
                    <annotation>@
                        <name>Override</name>
                    </annotation>
                    <specifier>public</specifier>
                    <name>MetaBean</name>
                </type>
                <name>metaBean</name>
                <parameter_list>()</parameter_list>
                <block>{
                    <return>return
                        <expr>
                            <name>metaBean</name>
                        </expr>
                        ;
                    </return>
                    }
                </block>
            </function>

            <function>
                <type>
                    <annotation>@
                        <name>Override</name>
                    </annotation>
                    <specifier>public</specifier>
                    <name>
                        <name>Class</name>
                        <argument_list>&lt;
                            <argument>
                                <name>?</name>
                            </argument>
                            &gt;
                        </argument_list>
                    </name>
                </type>
                <name>declaringType</name>
                <parameter_list>()</parameter_list>
                <block>{
                    <return>return
                        <expr>
                            <name>declaringType</name>
                        </expr>
                        ;
                    </return>
                    }
                </block>
            </function>

            <function>
                <type>
                    <annotation>@
                        <name>Override</name>
                    </annotation>
                    <specifier>public</specifier>
                    <name>
                        <name>Class</name>
                        <argument_list>&lt;
                            <argument>
                                <name>P</name>
                            </argument>
                            &gt;
                        </argument_list>
                    </name>
                </type>
                <name>propertyType</name>
                <parameter_list>()</parameter_list>
                <block>{
                    <return>return
                        <expr>
                            <name>propertyType</name>
                        </expr>
                        ;
                    </return>
                    }
                </block>
            </function>

            <function>
                <type>
                    <annotation>@
                        <name>Override</name>
                    </annotation>
                    <specifier>public</specifier>
                    <name>Type</name>
                </type>
                <name>propertyGenericType</name>
                <parameter_list>()</parameter_list>
                <block>{
                    <if>if
                        <condition>(
                            <expr>
                                <name>field</name>
                                ==
                                <name>null</name>
                            </expr>
                            )
                        </condition>
                        <then>
                            <block>{
                                <return>return
                                    <expr>
                                        <name>propertyType</name>
                                    </expr>
                                    ;
                                </return>
                                }
                            </block>
                        </then>
                    </if>
                    <return>return
                        <expr>
                            <call>
                                <name><name>field</name>.
                                    <name>getGenericType</name>
                                </name>
                                <argument_list>()</argument_list>
                            </call>
                        </expr>
                        ;
                    </return>
                    }
                </block>
            </function>

            <function>
                <type>
                    <annotation>@
                        <name>Override</name>
                    </annotation>
                    <specifier>public</specifier>
                    <name>PropertyStyle</name>
                </type>
                <name>style</name>
                <parameter_list>()</parameter_list>
                <block>{
                    <return>return
                        <expr>
                            <name>style</name>
                        </expr>
                        ;
                    </return>
                    }
                </block>
            </function>

            <function>
                <type>
                    <annotation>@
                        <name>Override</name>
                    </annotation>
                    <specifier>public</specifier>
                    <argument_list>&lt;
                        <argument>
                            <name>A</name>
                            <extends>extends
                                <name>Annotation</name>
                            </extends>
                        </argument>
                        &gt;
                    </argument_list>
                    <name>A</name>
                </type>
                <name>annotation</name>
                <parameter_list>(
                    <param>
                        <decl>
                            <type>
                                <name>
                                    <name>Class</name>
                                    <argument_list>&lt;
                                        <argument>
                                            <name>A</name>
                                        </argument>
                                        &gt;
                                    </argument_list>
                                </name>
                            </type>
                            <name>annotationClass</name>
                        </decl>
                    </param>
                    )
                </parameter_list>
                <block>{
                    <if>if
                        <condition>(
                            <expr>
                                <name>field</name>
                                ==
                                <name>null</name>
                            </expr>
                            )
                        </condition>
                        <then>
                            <block>{
                                <throw>throw
                                    <expr>new
                                        <call>
                                            <name>UnsupportedOperationException</name>
                                            <argument_list>(
                                                <argument>
                                                    <expr>"Field not found for property: " +
                                                        <call>
                                                            <name>name</name>
                                                            <argument_list>()</argument_list>
                                                        </call>
                                                    </expr>
                                                </argument>
                                                )
                                            </argument_list>
                                        </call>
                                    </expr>
                                    ;
                                </throw>
                                }
                            </block>
                        </then>
                    </if>
                    <decl_stmt>
                        <decl>
                            <type>
                                <name>A</name>
                            </type>
                            <name>annotation</name> =
                            <init>
                                <expr>
                                    <call>
                                        <name><name>field</name>.
                                            <name>getAnnotation</name>
                                        </name>
                                        <argument_list>(
                                            <argument>
                                                <expr>
                                                    <name>annotationClass</name>
                                                </expr>
                                            </argument>
                                            )
                                        </argument_list>
                                    </call>
                                </expr>
                            </init>
                        </decl>
                        ;
                    </decl_stmt>
                    <if>if
                        <condition>(
                            <expr>
                                <name>annotation</name>
                                ==
                                <name>null</name>
                            </expr>
                            )
                        </condition>
                        <then>
                            <block>{
                                <throw>throw
                                    <expr>new
                                        <call>
                                            <name>NoSuchElementException</name>
                                            <argument_list>(
                                                <argument>
                                                    <expr>"Unknown annotation: " +
                                                        <call>
                                                            <name><name>annotationClass</name>.
                                                                <name>getName</name>
                                                            </name>
                                                            <argument_list>()</argument_list>
                                                        </call>
                                                    </expr>
                                                </argument>
                                                )
                                            </argument_list>
                                        </call>
                                    </expr>
                                    ;
                                </throw>
                                }
                            </block>
                        </then>
                    </if>
                    <return>return
                        <expr>
                            <name>annotation</name>
                        </expr>
                        ;
                    </return>
                    }
                </block>
            </function>

            <function>
                <type>
                    <annotation>@
                        <name>Override</name>
                    </annotation>
                    <specifier>public</specifier>
                    <name>
                        <name>List</name>
                        <argument_list>&lt;
                            <argument>
                                <name>Annotation</name>
                            </argument>
                            &gt;
                        </argument_list>
                    </name>
                </type>
                <name>annotations</name>
                <parameter_list>()</parameter_list>
                <block>{
                    <if>if
                        <condition>(
                            <expr>
                                <name>field</name>
                                ==
                                <name>null</name>
                            </expr>
                            )
                        </condition>
                        <then>
                            <block>{
                                <return>return
                                    <expr>
                                        <call>
                                            <name><name>Collections</name>.
                                                <name>emptyList</name>
                                            </name>
                                            <argument_list>()</argument_list>
                                        </call>
                                    </expr>
                                    ;
                                </return>
                                }
                            </block>
                        </then>
                    </if>
                    <return>return
                        <expr>
                            <call>
                                <name><name>Arrays</name>.
                                    <name>asList</name>
                                </name>
                                <argument_list>(
                                    <argument>
                                        <expr>
                                            <call>
                                                <name><name>field</name>.
                                                    <name>getDeclaredAnnotations</name>
                                                </name>
                                                <argument_list>()</argument_list>
                                            </call>
                                        </expr>
                                    </argument>
                                    )
                                </argument_list>
                            </call>
                        </expr>
                        ;
                    </return>
                    }
                </block>
            </function>

            <comment type="line">//-----------------------------------------------------------------------</comment>
            <function>
                <type>
                    <annotation>@
                        <name>SuppressWarnings</name>
                        <argument_list>("unchecked")</argument_list>
                    </annotation>
                    <annotation>@
                        <name>Override</name>
                    </annotation>
                    <specifier>public</specifier>
                    <name>P</name>
                </type>
                <name>get</name>
                <parameter_list>(
                    <param>
                        <decl>
                            <type>
                                <name>Bean</name>
                            </type>
                            <name>bean</name>
                        </decl>
                    </param>
                    )
                </parameter_list>
                <block>{
                    <decl_stmt>
                        <decl>
                            <type>
                                <name>DirectMetaBean</name>
                            </type>
                            <name>meta</name> =
                            <init>
                                <expr>(<name>DirectMetaBean</name>)
                                    <call>
                                        <name><name>bean</name>.
                                            <name>metaBean</name>
                                        </name>
                                        <argument_list>()</argument_list>
                                    </call>
                                </expr>
                            </init>
                        </decl>
                        ;
                    </decl_stmt>
                    <return>return
                        <expr>(<name>P</name>)
                            <call>
                                <name><name>meta</name>.
                                    <name>propertyGet</name>
                                </name>
                                <argument_list>(
                                    <argument>
                                        <expr>
                                            <name>bean</name>
                                        </expr>
                                    </argument>
                                    ,
                                    <argument>
                                        <expr>
                                            <call>
                                                <name>name</name>
                                                <argument_list>()</argument_list>
                                            </call>
                                        </expr>
                                    </argument>
                                    ,
                                    <argument>
                                        <expr>false</expr>
                                    </argument>
                                    )
                                </argument_list>
                            </call>
                        </expr>
                        ;
                    </return>
                    }
                </block>
            </function>

            <function>
                <type>
                    <annotation>@
                        <name>Override</name>
                    </annotation>
                    <specifier>public</specifier>
                    <name>void</name>
                </type>
                <name>set</name>
                <parameter_list>(
                    <param>
                        <decl>
                            <type>
                                <name>Bean</name>
                            </type>
                            <name>bean</name>
                        </decl>
                    </param>
                    ,
                    <param>
                        <decl>
                            <type>
                                <name>Object</name>
                            </type>
                            <name>value</name>
                        </decl>
                    </param>
                    )
                </parameter_list>
                <block>{
                    <decl_stmt>
                        <decl>
                            <type>
                                <name>DirectMetaBean</name>
                            </type>
                            <name>meta</name> =
                            <init>
                                <expr>(<name>DirectMetaBean</name>)
                                    <call>
                                        <name><name>bean</name>.
                                            <name>metaBean</name>
                                        </name>
                                        <argument_list>()</argument_list>
                                    </call>
                                </expr>
                            </init>
                        </decl>
                        ;
                    </decl_stmt>
                    <expr_stmt>
                        <expr>
                            <call>
                                <name><name>meta</name>.
                                    <name>propertySet</name>
                                </name>
                                <argument_list>(
                                    <argument>
                                        <expr>
                                            <name>bean</name>
                                        </expr>
                                    </argument>
                                    ,
                                    <argument>
                                        <expr>
                                            <call>
                                                <name>name</name>
                                                <argument_list>()</argument_list>
                                            </call>
                                        </expr>
                                    </argument>
                                    ,
                                    <argument>
                                        <expr>
                                            <name>value</name>
                                        </expr>
                                    </argument>
                                    ,
                                    <argument>
                                        <expr>false</expr>
                                    </argument>
                                    )
                                </argument_list>
                            </call>
                        </expr>
                        ;
                    </expr_stmt>
                    }
                </block>
            </function>

            }
        </block>
    </class>
</unit>
