<?xml version="1.0" encoding="UTF-8" standalone="yes"?>
<unit xmlns="http://www.sdml.info/srcML/src" language="Java"
      filename="D:\bio\git\biorimp\BIO-RIMP\test_data\code\clogging\src\test\java\org\apache\commons\logging\simple\CustomConfigTestCase.java">
    <comment type="block">/*
        * Licensed to the Apache Software Foundation (ASF) under one or more
        * contributor license agreements. See the NOTICE file distributed with
        * this work for additional information regarding copyright ownership.
        * The ASF licenses this file to You under the Apache License, Version 2.0
        * (the "License"); you may not use this file except in compliance with
        * the License. You may obtain a copy of the License at
        *
        * http://www.apache.org/licenses/LICENSE-2.0
        *
        * Unless required by applicable law or agreed to in writing, software
        * distributed under the License is distributed on an "AS IS" BASIS,
        * WITHOUT WARRANTIES OR CONDITIONS OF ANY KIND, either express or implied.
        * See the License for the specific language governing permissions and
        * limitations under the License.
        */
    </comment>

    <package>package
        <name><name>org</name>.<name>apache</name>.<name>commons</name>.<name>logging</name>.
            <name>simple</name>
        </name>
        ;
    </package>


    <import>import
        <name><name>java</name>.<name>util</name>.
            <name>ArrayList</name>
        </name>
        ;
    </import>
    <import>import
        <name><name>java</name>.<name>util</name>.
            <name>Iterator</name>
        </name>
        ;
    </import>
    <import>import
        <name><name>java</name>.<name>util</name>.
            <name>List</name>
        </name>
        ;
    </import>

    <import>import
        <name><name>junit</name>.<name>framework</name>.
            <name>Test</name>
        </name>
        ;
    </import>

    <import>import
        <name><name>org</name>.<name>apache</name>.<name>commons</name>.<name>logging</name>.
            <name>DummyException</name>
        </name>
        ;
    </import>
    <import>import
        <name><name>org</name>.<name>apache</name>.<name>commons</name>.<name>logging</name>.
            <name>LogFactory</name>
        </name>
        ;
    </import>
    <import>import
        <name><name>org</name>.<name>apache</name>.<name>commons</name>.<name>logging</name>.
            <name>PathableClassLoader</name>
        </name>
        ;
    </import>
    <import>import
        <name><name>org</name>.<name>apache</name>.<name>commons</name>.<name>logging</name>.
            <name>PathableTestSuite</name>
        </name>
        ;
    </import>
    <import>import
        <name><name>org</name>.<name>apache</name>.<name>commons</name>.<name>logging</name>.<name>impl</name>.
            <name>SimpleLog</name>
        </name>
        ;
    </import>


    <comment type="javadoc">/**
        * &lt;p&gt;TestCase for simple logging when running with custom configuration
        * properties.&lt;/p&gt;
        *
        * @author Craig R. McClanahan
        * @version $Revision: 1432587 $ $Date: 2013-01-13 12:11:32 +0100 (Sun, 13 Jan 2013) $
        */
    </comment>
    <class>
        <specifier>public</specifier>
        class <name>CustomConfigTestCase</name>
        <super>
            <extends>extends
                <name>DefaultConfigTestCase</name>
            </extends>
        </super>
        <block>{


            <comment type="line">// ----------------------------------------------------- Instance Variables</comment>


            <comment type="javadoc">/**
                * &lt;p&gt;The expected log records.&lt;/p&gt;
                */
            </comment>
            <decl_stmt>
                <decl>
                    <type>
                        <specifier>protected</specifier>
                        <name>List</name>
                    </type>
                    <name>expected</name>
                </decl>
                ;
            </decl_stmt>


            <comment type="javadoc">/**
                * &lt;p&gt;The message levels that should have been logged.&lt;/p&gt;
                */
            </comment>
            <comment type="block">/*
                protected Level testLevels[] =
                { Level.FINE, Level.INFO, Level.WARNING, Level.SEVERE, Level.SEVERE };
                */
            </comment>


            <comment type="javadoc">/**
                * &lt;p&gt;The message strings that should have been logged.&lt;/p&gt;
                */
            </comment>
            <decl_stmt>
                <decl>
                    <type>
                        <specifier>protected</specifier>
                        <name>String</name>
                    </type>
                    <name>
                        <name>testMessages</name>
                        <index>[]</index>
                    </name>
                    =
                    <init>
                        <expr>
                            <block>{ <expr>"debug"</expr>, <expr>"info"</expr>, <expr>"warn"</expr>, <expr>
                                "error"</expr>, <expr>"fatal"</expr> }
                            </block>
                        </expr>
                    </init>
                </decl>
                ;
            </decl_stmt>


            <comment type="line">// ------------------------------------------- JUnit Infrastructure Methods</comment>

            <comment type="javadoc">/**
                * Set system properties that will control the LogFactory/Log objects
                * when they are created. Subclasses can override this method to
                * define properties that suit them.
                */
            </comment>
            <function>
                <type>
                    <specifier>public</specifier>
                    <name>void</name>
                </type>
                <name>setProperties</name>
                <parameter_list>()</parameter_list>
                <block>{
                    <expr_stmt>
                        <expr>
                            <call>
                                <name><name>System</name>.
                                    <name>setProperty</name>
                                </name>
                                <argument_list>(
                                    <argument>
                                        <expr>"org.apache.commons.logging.Log"</expr>
                                    </argument>
                                    ,
                                    <argument>
                                        <expr>"org.apache.commons.logging.simple.DecoratedSimpleLog"</expr>
                                    </argument>
                                    )
                                </argument_list>
                            </call>
                        </expr>
                        ;
                    </expr_stmt>
                    <expr_stmt>
                        <expr>
                            <call>
                                <name><name>System</name>.
                                    <name>setProperty</name>
                                </name>
                                <argument_list>(
                                    <argument>
                                        <expr>"org.apache.commons.logging.simplelog.defaultlog"</expr>
                                    </argument>
                                    ,
                                    <argument>
                                        <expr>"debug"</expr>
                                    </argument>
                                    )
                                </argument_list>
                            </call>
                        </expr>
                        ;
                    </expr_stmt>
                    }
                </block>
            </function>

            <comment type="javadoc">/**
                * Set up instance variables required by this test case.
                */
            </comment>
            <function>
                <type>
                    <specifier>public</specifier>
                    <name>void</name>
                </type>
                <name>setUp</name>
                <parameter_list>()</parameter_list>
                <throws>throws
                    <argument>
                        <expr>
                            <name>Exception</name>
                        </expr>
                    </argument>
                </throws>
                <block>{
                    <expr_stmt>
                        <expr>
                            <call>
                                <name><name>LogFactory</name>.
                                    <name>releaseAll</name>
                                </name>
                                <argument_list>()</argument_list>
                            </call>
                        </expr>
                        ;
                    </expr_stmt>
                    <expr_stmt>
                        <expr>
                            <call>
                                <name>setProperties</name>
                                <argument_list>()</argument_list>
                            </call>
                        </expr>
                        ;
                    </expr_stmt>
                    <expr_stmt>
                        <expr>
                            <name>expected</name>
                            = new
                            <call>
                                <name>ArrayList</name>
                                <argument_list>()</argument_list>
                            </call>
                        </expr>
                        ;
                    </expr_stmt>
                    <expr_stmt>
                        <expr>
                            <call>
                                <name>setUpFactory</name>
                                <argument_list>()</argument_list>
                            </call>
                        </expr>
                        ;
                    </expr_stmt>
                    <expr_stmt>
                        <expr>
                            <call>
                                <name>setUpLog</name>
                                <argument_list>(
                                    <argument>
                                        <expr>"DecoratedLogger"</expr>
                                    </argument>
                                    )
                                </argument_list>
                            </call>
                        </expr>
                        ;
                    </expr_stmt>
                    }
                </block>
            </function>


            <comment type="javadoc">/**
                * Return the tests included in this test suite.
                * &lt;p&gt;
                * We need to use a PathableClassLoader here because the SimpleLog class
                * is a pile of junk and chock-full of static variables. Any other test
                * (like simple.CustomConfigTestCase) that has used the SimpleLog class
                * will already have caused it to do once-only initialisation that we
                * can't reset, even by calling LogFactory.releaseAll, because of those
                * ugly statics. The only clean solution is to load a clean copy of
                * commons-logging including SimpleLog via a nice clean classloader.
                * Or we could fix SimpleLog to be sane...
                */
            </comment>
            <function>
                <type>
                    <specifier>public</specifier>
                    <specifier>static</specifier>
                    <name>Test</name>
                </type>
                <name>suite</name>
                <parameter_list>()</parameter_list>
                <throws>throws
                    <argument>
                        <expr>
                            <name>Exception</name>
                        </expr>
                    </argument>
                </throws>
                <block>{
                    <decl_stmt>
                        <decl>
                            <type>
                                <name>Class</name>
                            </type>
                            <name>thisClass</name> =
                            <init>
                                <expr>
                                    <name><name>CustomConfigTestCase</name>.
                                        <name>
                                            <name/>
                                        </name>
                                    </name>
                                    class
                                </expr>
                            </init>
                        </decl>
                        ;
                    </decl_stmt>

                    <decl_stmt>
                        <decl>
                            <type>
                                <name>PathableClassLoader</name>
                            </type>
                            <name>loader</name> =
                            <init>
                                <expr>new
                                    <call>
                                        <name>PathableClassLoader</name>
                                        <argument_list>(
                                            <argument>
                                                <expr>
                                                    <name>null</name>
                                                </expr>
                                            </argument>
                                            )
                                        </argument_list>
                                    </call>
                                </expr>
                            </init>
                        </decl>
                        ;
                    </decl_stmt>
                    <expr_stmt>
                        <expr>
                            <call>
                                <name><name>loader</name>.
                                    <name>useExplicitLoader</name>
                                </name>
                                <argument_list>(
                                    <argument>
                                        <expr>"junit."</expr>
                                    </argument>
                                    ,
                                    <argument>
                                        <expr>
                                            <name><name>Test</name>.
                                                <name>
                                                    <name/>
                                                </name>
                                            </name>
                                            class.
                                            <call>
                                                <name>getClassLoader</name>
                                                <argument_list>()</argument_list>
                                            </call>
                                        </expr>
                                    </argument>
                                    )
                                </argument_list>
                            </call>
                        </expr>
                        ;
                    </expr_stmt>
                    <expr_stmt>
                        <expr>
                            <call>
                                <name><name>loader</name>.
                                    <name>addLogicalLib</name>
                                </name>
                                <argument_list>(
                                    <argument>
                                        <expr>"testclasses"</expr>
                                    </argument>
                                    )
                                </argument_list>
                            </call>
                        </expr>
                        ;
                    </expr_stmt>
                    <expr_stmt>
                        <expr>
                            <call>
                                <name><name>loader</name>.
                                    <name>addLogicalLib</name>
                                </name>
                                <argument_list>(
                                    <argument>
                                        <expr>"commons-logging"</expr>
                                    </argument>
                                    )
                                </argument_list>
                            </call>
                        </expr>
                        ;
                    </expr_stmt>

                    <decl_stmt>
                        <decl>
                            <type>
                                <name>Class</name>
                            </type>
                            <name>testClass</name> =
                            <init>
                                <expr>
                                    <call>
                                        <name><name>loader</name>.
                                            <name>loadClass</name>
                                        </name>
                                        <argument_list>(
                                            <argument>
                                                <expr>
                                                    <call>
                                                        <name><name>thisClass</name>.
                                                            <name>getName</name>
                                                        </name>
                                                        <argument_list>()</argument_list>
                                                    </call>
                                                </expr>
                                            </argument>
                                            )
                                        </argument_list>
                                    </call>
                                </expr>
                            </init>
                        </decl>
                        ;
                    </decl_stmt>
                    <return>return
                        <expr>new
                            <call>
                                <name>PathableTestSuite</name>
                                <argument_list>(
                                    <argument>
                                        <expr>
                                            <name>testClass</name>
                                        </expr>
                                    </argument>
                                    ,
                                    <argument>
                                        <expr>
                                            <name>loader</name>
                                        </expr>
                                    </argument>
                                    )
                                </argument_list>
                            </call>
                        </expr>
                        ;
                    </return>
                    }
                </block>
            </function>

            <comment type="javadoc">/**
                * Tear down instance variables required by this test case.
                */
            </comment>
            <function>
                <type>
                    <specifier>public</specifier>
                    <name>void</name>
                </type>
                <name>tearDown</name>
                <parameter_list>()</parameter_list>
                <block>{
                    <expr_stmt>
                        <expr>
                            <call>
                                <name><name>super</name>.
                                    <name>tearDown</name>
                                </name>
                                <argument_list>()</argument_list>
                            </call>
                        </expr>
                        ;
                    </expr_stmt>
                    <expr_stmt>
                        <expr>
                            <name>expected</name>
                            =
                            <name>null</name>
                        </expr>
                        ;
                    </expr_stmt>
                    }
                </block>
            </function>


            <comment type="line">// ----------------------------------------------------------- Test Methods</comment>


            <comment type="line">// Test logging message strings with exceptions</comment>
            <function>
                <type>
                    <specifier>public</specifier>
                    <name>void</name>
                </type>
                <name>testExceptionMessages</name>
                <parameter_list>()</parameter_list>
                <throws>throws
                    <argument>
                        <expr>
                            <name>Exception</name>
                        </expr>
                    </argument>
                </throws>
                <block>{

                    <expr_stmt>
                        <expr>((<name>DecoratedSimpleLog</name>) <name>log</name>).
                            <call>
                                <name>clearCache</name>
                                <argument_list>()</argument_list>
                            </call>
                        </expr>
                        ;
                    </expr_stmt>
                    <expr_stmt>
                        <expr>
                            <call>
                                <name>logExceptionMessages</name>
                                <argument_list>()</argument_list>
                            </call>
                        </expr>
                        ;
                    </expr_stmt>
                    <expr_stmt>
                        <expr>
                            <call>
                                <name>checkExpected</name>
                                <argument_list>()</argument_list>
                            </call>
                        </expr>
                        ;
                    </expr_stmt>

                    }
                </block>
            </function>


            <comment type="line">// Test logging plain message strings</comment>
            <function>
                <type>
                    <specifier>public</specifier>
                    <name>void</name>
                </type>
                <name>testPlainMessages</name>
                <parameter_list>()</parameter_list>
                <throws>throws
                    <argument>
                        <expr>
                            <name>Exception</name>
                        </expr>
                    </argument>
                </throws>
                <block>{

                    <expr_stmt>
                        <expr>((<name>DecoratedSimpleLog</name>) <name>log</name>).
                            <call>
                                <name>clearCache</name>
                                <argument_list>()</argument_list>
                            </call>
                        </expr>
                        ;
                    </expr_stmt>
                    <expr_stmt>
                        <expr>
                            <call>
                                <name>logPlainMessages</name>
                                <argument_list>()</argument_list>
                            </call>
                        </expr>
                        ;
                    </expr_stmt>
                    <expr_stmt>
                        <expr>
                            <call>
                                <name>checkExpected</name>
                                <argument_list>()</argument_list>
                            </call>
                        </expr>
                        ;
                    </expr_stmt>

                    }
                </block>
            </function>


            <comment type="line">// Test Serializability of standard instance</comment>
            <function>
                <type>
                    <specifier>public</specifier>
                    <name>void</name>
                </type>
                <name>testSerializable</name>
                <parameter_list>()</parameter_list>
                <throws>throws
                    <argument>
                        <expr>
                            <name>Exception</name>
                        </expr>
                    </argument>
                </throws>
                <block>{

                    <expr_stmt>
                        <expr>((<name>DecoratedSimpleLog</name>) <name>log</name>).
                            <call>
                                <name>clearCache</name>
                                <argument_list>()</argument_list>
                            </call>
                        </expr>
                        ;
                    </expr_stmt>
                    <expr_stmt>
                        <expr>
                            <call>
                                <name>logPlainMessages</name>
                                <argument_list>()</argument_list>
                            </call>
                        </expr>
                        ;
                    </expr_stmt>
                    <expr_stmt>
                        <expr>
                            <call>
                                <name><name>super</name>.
                                    <name>testSerializable</name>
                                </name>
                                <argument_list>()</argument_list>
                            </call>
                        </expr>
                        ;
                    </expr_stmt>
                    <expr_stmt>
                        <expr>
                            <call>
                                <name>logExceptionMessages</name>
                                <argument_list>()</argument_list>
                            </call>
                        </expr>
                        ;
                    </expr_stmt>
                    <expr_stmt>
                        <expr>
                            <call>
                                <name>checkExpected</name>
                                <argument_list>()</argument_list>
                            </call>
                        </expr>
                        ;
                    </expr_stmt>

                    }
                </block>
            </function>


            <comment type="line">// -------------------------------------------------------- Support Methods</comment>


            <comment type="line">// Check the decorated log instance</comment>
            <function>
                <type>
                    <specifier>protected</specifier>
                    <name>void</name>
                </type>
                <name>checkDecorated</name>
                <parameter_list>()</parameter_list>
                <block>{

                    <expr_stmt>
                        <expr>
                            <call>
                                <name>assertNotNull</name>
                                <argument_list>(
                                    <argument>
                                        <expr>"Log exists"</expr>
                                    </argument>
                                    ,
                                    <argument>
                                        <expr>
                                            <name>log</name>
                                        </expr>
                                    </argument>
                                    )
                                </argument_list>
                            </call>
                        </expr>
                        ;
                    </expr_stmt>
                    <expr_stmt>
                        <expr>
                            <call>
                                <name>assertEquals</name>
                                <argument_list>(
                                    <argument>
                                        <expr>"Log class"</expr>
                                    </argument>
                                    ,
                                    <argument>
                                        <expr>"org.apache.commons.logging.simple.DecoratedSimpleLog"</expr>
                                    </argument>
                                    ,
                                    <argument>
                                        <expr>
                                            <call>
                                                <name><name>log</name>.
                                                    <name>getClass</name>
                                                </name>
                                                <argument_list>()</argument_list>
                                            </call>
                                            .
                                            <call>
                                                <name>getName</name>
                                                <argument_list>()</argument_list>
                                            </call>
                                        </expr>
                                    </argument>
                                    )
                                </argument_list>
                            </call>
                        </expr>
                        ;
                    </expr_stmt>

                    <comment type="line">// Can we call level checkers with no exceptions?</comment>
                    <expr_stmt>
                        <expr>
                            <call>
                                <name>assertTrue</name>
                                <argument_list>(
                                    <argument>
                                        <expr>
                                            <call>
                                                <name><name>log</name>.
                                                    <name>isDebugEnabled</name>
                                                </name>
                                                <argument_list>()</argument_list>
                                            </call>
                                        </expr>
                                    </argument>
                                    )
                                </argument_list>
                            </call>
                        </expr>
                        ;
                    </expr_stmt>
                    <expr_stmt>
                        <expr>
                            <call>
                                <name>assertTrue</name>
                                <argument_list>(
                                    <argument>
                                        <expr>
                                            <call>
                                                <name><name>log</name>.
                                                    <name>isErrorEnabled</name>
                                                </name>
                                                <argument_list>()</argument_list>
                                            </call>
                                        </expr>
                                    </argument>
                                    )
                                </argument_list>
                            </call>
                        </expr>
                        ;
                    </expr_stmt>
                    <expr_stmt>
                        <expr>
                            <call>
                                <name>assertTrue</name>
                                <argument_list>(
                                    <argument>
                                        <expr>
                                            <call>
                                                <name><name>log</name>.
                                                    <name>isFatalEnabled</name>
                                                </name>
                                                <argument_list>()</argument_list>
                                            </call>
                                        </expr>
                                    </argument>
                                    )
                                </argument_list>
                            </call>
                        </expr>
                        ;
                    </expr_stmt>
                    <expr_stmt>
                        <expr>
                            <call>
                                <name>assertTrue</name>
                                <argument_list>(
                                    <argument>
                                        <expr>
                                            <call>
                                                <name><name>log</name>.
                                                    <name>isInfoEnabled</name>
                                                </name>
                                                <argument_list>()</argument_list>
                                            </call>
                                        </expr>
                                    </argument>
                                    )
                                </argument_list>
                            </call>
                        </expr>
                        ;
                    </expr_stmt>
                    <expr_stmt>
                        <expr>
                            <call>
                                <name>assertTrue</name>
                                <argument_list>(
                                    <argument>
                                        <expr>!
                                            <call>
                                                <name><name>log</name>.
                                                    <name>isTraceEnabled</name>
                                                </name>
                                                <argument_list>()</argument_list>
                                            </call>
                                        </expr>
                                    </argument>
                                    )
                                </argument_list>
                            </call>
                        </expr>
                        ;
                    </expr_stmt>
                    <expr_stmt>
                        <expr>
                            <call>
                                <name>assertTrue</name>
                                <argument_list>(
                                    <argument>
                                        <expr>
                                            <call>
                                                <name><name>log</name>.
                                                    <name>isWarnEnabled</name>
                                                </name>
                                                <argument_list>()</argument_list>
                                            </call>
                                        </expr>
                                    </argument>
                                    )
                                </argument_list>
                            </call>
                        </expr>
                        ;
                    </expr_stmt>

                    <comment type="line">// Can we retrieve the current log level?</comment>
                    <expr_stmt>
                        <expr>
                            <call>
                                <name>assertEquals</name>
                                <argument_list>(
                                    <argument>
                                        <expr>
                                            <name><name>SimpleLog</name>.
                                                <name>LOG_LEVEL_DEBUG</name>
                                            </name>
                                        </expr>
                                    </argument>
                                    ,
                                    <argument>
                                        <expr>((<name>SimpleLog</name>) <name>log</name>).
                                            <call>
                                                <name>getLevel</name>
                                                <argument_list>()</argument_list>
                                            </call>
                                        </expr>
                                    </argument>
                                    )
                                </argument_list>
                            </call>
                        </expr>
                        ;
                    </expr_stmt>

                    <comment type="line">// Can we validate the extra exposed properties?</comment>
                    <expr_stmt>
                        <expr>
                            <call>
                                <name>checkDecoratedDateTime</name>
                                <argument_list>()</argument_list>
                            </call>
                        </expr>
                        ;
                    </expr_stmt>
                    <expr_stmt>
                        <expr>
                            <call>
                                <name>assertEquals</name>
                                <argument_list>(
                                    <argument>
                                        <expr>"DecoratedLogger"</expr>
                                    </argument>
                                    ,
                                    <argument>
                                        <expr>((<name>DecoratedSimpleLog</name>) <name>log</name>).
                                            <call>
                                                <name>getLogName</name>
                                                <argument_list>()</argument_list>
                                            </call>
                                        </expr>
                                    </argument>
                                    )
                                </argument_list>
                            </call>
                        </expr>
                        ;
                    </expr_stmt>
                    <expr_stmt>
                        <expr>
                            <call>
                                <name>checkShowDateTime</name>
                                <argument_list>()</argument_list>
                            </call>
                        </expr>
                        ;
                    </expr_stmt>
                    <expr_stmt>
                        <expr>
                            <call>
                                <name>assertTrue</name>
                                <argument_list>(
                                    <argument>
                                        <expr>((<name>DecoratedSimpleLog</name>) <name>log</name>).
                                            <call>
                                                <name>getShowShortName</name>
                                                <argument_list>()</argument_list>
                                            </call>
                                        </expr>
                                    </argument>
                                    )
                                </argument_list>
                            </call>
                        </expr>
                        ;
                    </expr_stmt>

                    }
                </block>
            </function>

            <comment type="javadoc">/** Hook for subclassses */</comment>
            <function>
                <type>
                    <specifier>protected</specifier>
                    <name>void</name>
                </type>
                <name>checkShowDateTime</name>
                <parameter_list>()</parameter_list>
                <block>{
                    <expr_stmt>
                        <expr>
                            <call>
                                <name>assertTrue</name>
                                <argument_list>(
                                    <argument>
                                        <expr>!((<name>DecoratedSimpleLog</name>) <name>log</name>).
                                            <call>
                                                <name>getShowDateTime</name>
                                                <argument_list>()</argument_list>
                                            </call>
                                        </expr>
                                    </argument>
                                    )
                                </argument_list>
                            </call>
                        </expr>
                        ;
                    </expr_stmt>
                    }
                </block>
            </function>

            <comment type="javadoc">/** Hook for subclasses */</comment>
            <function>
                <type>
                    <specifier>protected</specifier>
                    <name>void</name>
                </type>
                <name>checkDecoratedDateTime</name>
                <parameter_list>()</parameter_list>
                <block>{
                    <expr_stmt>
                        <expr>
                            <call>
                                <name>assertEquals</name>
                                <argument_list>(
                                    <argument>
                                        <expr>"yyyy/MM/dd HH:mm:ss:SSS zzz"</expr>
                                    </argument>
                                    ,
                                    <argument>
                                        <expr>((<name>DecoratedSimpleLog</name>) <name>log</name>).
                                            <call>
                                                <name>getDateTimeFormat</name>
                                                <argument_list>()</argument_list>
                                            </call>
                                        </expr>
                                    </argument>
                                    )
                                </argument_list>
                            </call>
                        </expr>
                        ;
                    </expr_stmt>
                    }
                </block>
            </function>


            <comment type="line">// Check the actual log records against the expected ones</comment>
            <function>
                <type>
                    <specifier>protected</specifier>
                    <name>void</name>
                </type>
                <name>checkExpected</name>
                <parameter_list>()</parameter_list>
                <block>{

                    <decl_stmt>
                        <decl>
                            <type>
                                <name>List</name>
                            </type>
                            <name>acts</name> =
                            <init>
                                <expr>((<name>DecoratedSimpleLog</name>) <name>log</name>).
                                    <call>
                                        <name>getCache</name>
                                        <argument_list>()</argument_list>
                                    </call>
                                </expr>
                            </init>
                        </decl>
                        ;
                    </decl_stmt>
                    <decl_stmt>
                        <decl>
                            <type>
                                <name>Iterator</name>
                            </type>
                            <name>exps</name> =
                            <init>
                                <expr>
                                    <call>
                                        <name><name>expected</name>.
                                            <name>iterator</name>
                                        </name>
                                        <argument_list>()</argument_list>
                                    </call>
                                </expr>
                            </init>
                        </decl>
                        ;
                    </decl_stmt>
                    <decl_stmt>
                        <decl>
                            <type>
                                <name>int</name>
                            </type>
                            <name>n</name> =
                            <init>
                                <expr>0</expr>
                            </init>
                        </decl>
                        ;
                    </decl_stmt>
                    <while>while
                        <condition>(
                            <expr>
                                <call>
                                    <name><name>exps</name>.
                                        <name>hasNext</name>
                                    </name>
                                    <argument_list>()</argument_list>
                                </call>
                            </expr>
                            )
                        </condition>
                        <block>{
                            <decl_stmt>
                                <decl>
                                    <type>
                                        <name>LogRecord</name>
                                    </type>
                                    <name>exp</name> =
                                    <init>
                                        <expr>(<name>LogRecord</name>)
                                            <call>
                                                <name><name>exps</name>.
                                                    <name>next</name>
                                                </name>
                                                <argument_list>()</argument_list>
                                            </call>
                                        </expr>
                                    </init>
                                </decl>
                                ;
                            </decl_stmt>
                            <decl_stmt>
                                <decl>
                                    <type>
                                        <name>LogRecord</name>
                                    </type>
                                    <name>act</name> =
                                    <init>
                                        <expr>(<name>LogRecord</name>)
                                            <call>
                                                <name><name>acts</name>.
                                                    <name>get</name>
                                                </name>
                                                <argument_list>(
                                                    <argument>
                                                        <expr><name>n</name>++
                                                        </expr>
                                                    </argument>
                                                    )
                                                </argument_list>
                                            </call>
                                        </expr>
                                    </init>
                                </decl>
                                ;
                            </decl_stmt>
                            <expr_stmt>
                                <expr>
                                    <call>
                                        <name>assertEquals</name>
                                        <argument_list>(
                                            <argument>
                                                <expr>"Row " + <name>n</name> + " type"
                                                </expr>
                                            </argument>
                                            ,
                                            <argument>
                                                <expr>
                                                    <name><name>exp</name>.
                                                        <name>type</name>
                                                    </name>
                                                </expr>
                                            </argument>
                                            ,
                                            <argument>
                                                <expr>
                                                    <name><name>act</name>.
                                                        <name>type</name>
                                                    </name>
                                                </expr>
                                            </argument>
                                            )
                                        </argument_list>
                                    </call>
                                </expr>
                                ;
                            </expr_stmt>
                            <expr_stmt>
                                <expr>
                                    <call>
                                        <name>assertEquals</name>
                                        <argument_list>(
                                            <argument>
                                                <expr>"Row " + <name>n</name> + " message"
                                                </expr>
                                            </argument>
                                            ,
                                            <argument>
                                                <expr>
                                                    <name><name>exp</name>.
                                                        <name>message</name>
                                                    </name>
                                                </expr>
                                            </argument>
                                            ,
                                            <argument>
                                                <expr>
                                                    <name><name>act</name>.
                                                        <name>message</name>
                                                    </name>
                                                </expr>
                                            </argument>
                                            )
                                        </argument_list>
                                    </call>
                                </expr>
                                ;
                            </expr_stmt>
                            <expr_stmt>
                                <expr>
                                    <call>
                                        <name>assertEquals</name>
                                        <argument_list>(
                                            <argument>
                                                <expr>"Row " + <name>n</name> + " throwable"
                                                </expr>
                                            </argument>
                                            ,
                                            <argument>
                                                <expr>
                                                    <name><name>exp</name>.
                                                        <name>t</name>
                                                    </name>
                                                </expr>
                                            </argument>
                                            ,
                                            <argument>
                                                <expr>
                                                    <name><name>act</name>.
                                                        <name>t</name>
                                                    </name>
                                                </expr>
                                            </argument>
                                            )
                                        </argument_list>
                                    </call>
                                </expr>
                                ;
                            </expr_stmt>
                            }
                        </block>
                    </while>

                    }
                </block>
            </function>


            <comment type="line">// Check the standard log instance</comment>
            <function>
                <type>
                    <specifier>protected</specifier>
                    <name>void</name>
                </type>
                <name>checkStandard</name>
                <parameter_list>()</parameter_list>
                <block>{

                    <expr_stmt>
                        <expr>
                            <call>
                                <name>checkDecorated</name>
                                <argument_list>()</argument_list>
                            </call>
                        </expr>
                        ;
                    </expr_stmt>

                    }
                </block>
            </function>


            <comment type="line">// Log the messages with exceptions</comment>
            <function>
                <type>
                    <specifier>protected</specifier>
                    <name>void</name>
                </type>
                <name>logExceptionMessages</name>
                <parameter_list>()</parameter_list>
                <block>{

                    <comment type="line">// Generate log records</comment>
                    <decl_stmt>
                        <decl>
                            <type>
                                <name>Throwable</name>
                            </type>
                            <name>t</name> =
                            <init>
                                <expr>new
                                    <call>
                                        <name>DummyException</name>
                                        <argument_list>()</argument_list>
                                    </call>
                                </expr>
                            </init>
                        </decl>
                        ;
                    </decl_stmt>
                    <expr_stmt>
                        <expr>
                            <call>
                                <name><name>log</name>.
                                    <name>trace</name>
                                </name>
                                <argument_list>(
                                    <argument>
                                        <expr>"trace"</expr>
                                    </argument>
                                    ,
                                    <argument>
                                        <expr>
                                            <name>t</name>
                                        </expr>
                                    </argument>
                                    )
                                </argument_list>
                            </call>
                        </expr>
                        ;
                    </expr_stmt>
                    <comment type="line">// Should not actually get logged</comment>
                    <expr_stmt>
                        <expr>
                            <call>
                                <name><name>log</name>.
                                    <name>debug</name>
                                </name>
                                <argument_list>(
                                    <argument>
                                        <expr>"debug"</expr>
                                    </argument>
                                    ,
                                    <argument>
                                        <expr>
                                            <name>t</name>
                                        </expr>
                                    </argument>
                                    )
                                </argument_list>
                            </call>
                        </expr>
                        ;
                    </expr_stmt>
                    <expr_stmt>
                        <expr>
                            <call>
                                <name><name>log</name>.
                                    <name>info</name>
                                </name>
                                <argument_list>(
                                    <argument>
                                        <expr>"info"</expr>
                                    </argument>
                                    ,
                                    <argument>
                                        <expr>
                                            <name>t</name>
                                        </expr>
                                    </argument>
                                    )
                                </argument_list>
                            </call>
                        </expr>
                        ;
                    </expr_stmt>
                    <expr_stmt>
                        <expr>
                            <call>
                                <name><name>log</name>.
                                    <name>warn</name>
                                </name>
                                <argument_list>(
                                    <argument>
                                        <expr>"warn"</expr>
                                    </argument>
                                    ,
                                    <argument>
                                        <expr>
                                            <name>t</name>
                                        </expr>
                                    </argument>
                                    )
                                </argument_list>
                            </call>
                        </expr>
                        ;
                    </expr_stmt>
                    <expr_stmt>
                        <expr>
                            <call>
                                <name><name>log</name>.
                                    <name>error</name>
                                </name>
                                <argument_list>(
                                    <argument>
                                        <expr>"error"</expr>
                                    </argument>
                                    ,
                                    <argument>
                                        <expr>
                                            <name>t</name>
                                        </expr>
                                    </argument>
                                    )
                                </argument_list>
                            </call>
                        </expr>
                        ;
                    </expr_stmt>
                    <expr_stmt>
                        <expr>
                            <call>
                                <name><name>log</name>.
                                    <name>fatal</name>
                                </name>
                                <argument_list>(
                                    <argument>
                                        <expr>"fatal"</expr>
                                    </argument>
                                    ,
                                    <argument>
                                        <expr>
                                            <name>t</name>
                                        </expr>
                                    </argument>
                                    )
                                </argument_list>
                            </call>
                        </expr>
                        ;
                    </expr_stmt>

                    <comment type="line">// Record the log records we expect</comment>
                    <expr_stmt>
                        <expr>
                            <call>
                                <name><name>expected</name>.
                                    <name>add</name>
                                </name>
                                <argument_list>(
                                    <argument>
                                        <expr>new
                                            <call>
                                                <name>LogRecord</name>
                                                <argument_list>(
                                                    <argument>
                                                        <expr>
                                                            <name><name>SimpleLog</name>.
                                                                <name>LOG_LEVEL_DEBUG</name>
                                                            </name>
                                                        </expr>
                                                    </argument>
                                                    ,
                                                    <argument>
                                                        <expr>"debug"</expr>
                                                    </argument>
                                                    ,
                                                    <argument>
                                                        <expr>
                                                            <name>t</name>
                                                        </expr>
                                                    </argument>
                                                    )
                                                </argument_list>
                                            </call>
                                        </expr>
                                    </argument>
                                    )
                                </argument_list>
                            </call>
                        </expr>
                        ;
                    </expr_stmt>
                    <expr_stmt>
                        <expr>
                            <call>
                                <name><name>expected</name>.
                                    <name>add</name>
                                </name>
                                <argument_list>(
                                    <argument>
                                        <expr>new
                                            <call>
                                                <name>LogRecord</name>
                                                <argument_list>(
                                                    <argument>
                                                        <expr>
                                                            <name><name>SimpleLog</name>.
                                                                <name>LOG_LEVEL_INFO</name>
                                                            </name>
                                                        </expr>
                                                    </argument>
                                                    ,
                                                    <argument>
                                                        <expr>"info"</expr>
                                                    </argument>
                                                    ,
                                                    <argument>
                                                        <expr>
                                                            <name>t</name>
                                                        </expr>
                                                    </argument>
                                                    )
                                                </argument_list>
                                            </call>
                                        </expr>
                                    </argument>
                                    )
                                </argument_list>
                            </call>
                        </expr>
                        ;
                    </expr_stmt>
                    <expr_stmt>
                        <expr>
                            <call>
                                <name><name>expected</name>.
                                    <name>add</name>
                                </name>
                                <argument_list>(
                                    <argument>
                                        <expr>new
                                            <call>
                                                <name>LogRecord</name>
                                                <argument_list>(
                                                    <argument>
                                                        <expr>
                                                            <name><name>SimpleLog</name>.
                                                                <name>LOG_LEVEL_WARN</name>
                                                            </name>
                                                        </expr>
                                                    </argument>
                                                    ,
                                                    <argument>
                                                        <expr>"warn"</expr>
                                                    </argument>
                                                    ,
                                                    <argument>
                                                        <expr>
                                                            <name>t</name>
                                                        </expr>
                                                    </argument>
                                                    )
                                                </argument_list>
                                            </call>
                                        </expr>
                                    </argument>
                                    )
                                </argument_list>
                            </call>
                        </expr>
                        ;
                    </expr_stmt>
                    <expr_stmt>
                        <expr>
                            <call>
                                <name><name>expected</name>.
                                    <name>add</name>
                                </name>
                                <argument_list>(
                                    <argument>
                                        <expr>new
                                            <call>
                                                <name>LogRecord</name>
                                                <argument_list>(
                                                    <argument>
                                                        <expr>
                                                            <name><name>SimpleLog</name>.
                                                                <name>LOG_LEVEL_ERROR</name>
                                                            </name>
                                                        </expr>
                                                    </argument>
                                                    ,
                                                    <argument>
                                                        <expr>"error"</expr>
                                                    </argument>
                                                    ,
                                                    <argument>
                                                        <expr>
                                                            <name>t</name>
                                                        </expr>
                                                    </argument>
                                                    )
                                                </argument_list>
                                            </call>
                                        </expr>
                                    </argument>
                                    )
                                </argument_list>
                            </call>
                        </expr>
                        ;
                    </expr_stmt>
                    <expr_stmt>
                        <expr>
                            <call>
                                <name><name>expected</name>.
                                    <name>add</name>
                                </name>
                                <argument_list>(
                                    <argument>
                                        <expr>new
                                            <call>
                                                <name>LogRecord</name>
                                                <argument_list>(
                                                    <argument>
                                                        <expr>
                                                            <name><name>SimpleLog</name>.
                                                                <name>LOG_LEVEL_FATAL</name>
                                                            </name>
                                                        </expr>
                                                    </argument>
                                                    ,
                                                    <argument>
                                                        <expr>"fatal"</expr>
                                                    </argument>
                                                    ,
                                                    <argument>
                                                        <expr>
                                                            <name>t</name>
                                                        </expr>
                                                    </argument>
                                                    )
                                                </argument_list>
                                            </call>
                                        </expr>
                                    </argument>
                                    )
                                </argument_list>
                            </call>
                        </expr>
                        ;
                    </expr_stmt>

                    }
                </block>
            </function>


            <comment type="line">// Log the plain messages</comment>
            <function>
                <type>
                    <specifier>protected</specifier>
                    <name>void</name>
                </type>
                <name>logPlainMessages</name>
                <parameter_list>()</parameter_list>
                <block>{

                    <comment type="line">// Generate log records</comment>
                    <expr_stmt>
                        <expr>
                            <call>
                                <name><name>log</name>.
                                    <name>trace</name>
                                </name>
                                <argument_list>(
                                    <argument>
                                        <expr>"trace"</expr>
                                    </argument>
                                    )
                                </argument_list>
                            </call>
                        </expr>
                        ;
                    </expr_stmt>
                    <comment type="line">// Should not actually get logged</comment>
                    <expr_stmt>
                        <expr>
                            <call>
                                <name><name>log</name>.
                                    <name>debug</name>
                                </name>
                                <argument_list>(
                                    <argument>
                                        <expr>"debug"</expr>
                                    </argument>
                                    )
                                </argument_list>
                            </call>
                        </expr>
                        ;
                    </expr_stmt>
                    <expr_stmt>
                        <expr>
                            <call>
                                <name><name>log</name>.
                                    <name>info</name>
                                </name>
                                <argument_list>(
                                    <argument>
                                        <expr>"info"</expr>
                                    </argument>
                                    )
                                </argument_list>
                            </call>
                        </expr>
                        ;
                    </expr_stmt>
                    <expr_stmt>
                        <expr>
                            <call>
                                <name><name>log</name>.
                                    <name>warn</name>
                                </name>
                                <argument_list>(
                                    <argument>
                                        <expr>"warn"</expr>
                                    </argument>
                                    )
                                </argument_list>
                            </call>
                        </expr>
                        ;
                    </expr_stmt>
                    <expr_stmt>
                        <expr>
                            <call>
                                <name><name>log</name>.
                                    <name>error</name>
                                </name>
                                <argument_list>(
                                    <argument>
                                        <expr>"error"</expr>
                                    </argument>
                                    )
                                </argument_list>
                            </call>
                        </expr>
                        ;
                    </expr_stmt>
                    <expr_stmt>
                        <expr>
                            <call>
                                <name><name>log</name>.
                                    <name>fatal</name>
                                </name>
                                <argument_list>(
                                    <argument>
                                        <expr>"fatal"</expr>
                                    </argument>
                                    )
                                </argument_list>
                            </call>
                        </expr>
                        ;
                    </expr_stmt>

                    <comment type="line">// Record the log records we expect</comment>
                    <expr_stmt>
                        <expr>
                            <call>
                                <name><name>expected</name>.
                                    <name>add</name>
                                </name>
                                <argument_list>(
                                    <argument>
                                        <expr>new
                                            <call>
                                                <name>LogRecord</name>
                                                <argument_list>(
                                                    <argument>
                                                        <expr>
                                                            <name><name>SimpleLog</name>.
                                                                <name>LOG_LEVEL_DEBUG</name>
                                                            </name>
                                                        </expr>
                                                    </argument>
                                                    ,
                                                    <argument>
                                                        <expr>"debug"</expr>
                                                    </argument>
                                                    ,
                                                    <argument>
                                                        <expr>
                                                            <name>null</name>
                                                        </expr>
                                                    </argument>
                                                    )
                                                </argument_list>
                                            </call>
                                        </expr>
                                    </argument>
                                    )
                                </argument_list>
                            </call>
                        </expr>
                        ;
                    </expr_stmt>
                    <expr_stmt>
                        <expr>
                            <call>
                                <name><name>expected</name>.
                                    <name>add</name>
                                </name>
                                <argument_list>(
                                    <argument>
                                        <expr>new
                                            <call>
                                                <name>LogRecord</name>
                                                <argument_list>(
                                                    <argument>
                                                        <expr>
                                                            <name><name>SimpleLog</name>.
                                                                <name>LOG_LEVEL_INFO</name>
                                                            </name>
                                                        </expr>
                                                    </argument>
                                                    ,
                                                    <argument>
                                                        <expr>"info"</expr>
                                                    </argument>
                                                    ,
                                                    <argument>
                                                        <expr>
                                                            <name>null</name>
                                                        </expr>
                                                    </argument>
                                                    )
                                                </argument_list>
                                            </call>
                                        </expr>
                                    </argument>
                                    )
                                </argument_list>
                            </call>
                        </expr>
                        ;
                    </expr_stmt>
                    <expr_stmt>
                        <expr>
                            <call>
                                <name><name>expected</name>.
                                    <name>add</name>
                                </name>
                                <argument_list>(
                                    <argument>
                                        <expr>new
                                            <call>
                                                <name>LogRecord</name>
                                                <argument_list>(
                                                    <argument>
                                                        <expr>
                                                            <name><name>SimpleLog</name>.
                                                                <name>LOG_LEVEL_WARN</name>
                                                            </name>
                                                        </expr>
                                                    </argument>
                                                    ,
                                                    <argument>
                                                        <expr>"warn"</expr>
                                                    </argument>
                                                    ,
                                                    <argument>
                                                        <expr>
                                                            <name>null</name>
                                                        </expr>
                                                    </argument>
                                                    )
                                                </argument_list>
                                            </call>
                                        </expr>
                                    </argument>
                                    )
                                </argument_list>
                            </call>
                        </expr>
                        ;
                    </expr_stmt>
                    <expr_stmt>
                        <expr>
                            <call>
                                <name><name>expected</name>.
                                    <name>add</name>
                                </name>
                                <argument_list>(
                                    <argument>
                                        <expr>new
                                            <call>
                                                <name>LogRecord</name>
                                                <argument_list>(
                                                    <argument>
                                                        <expr>
                                                            <name><name>SimpleLog</name>.
                                                                <name>LOG_LEVEL_ERROR</name>
                                                            </name>
                                                        </expr>
                                                    </argument>
                                                    ,
                                                    <argument>
                                                        <expr>"error"</expr>
                                                    </argument>
                                                    ,
                                                    <argument>
                                                        <expr>
                                                            <name>null</name>
                                                        </expr>
                                                    </argument>
                                                    )
                                                </argument_list>
                                            </call>
                                        </expr>
                                    </argument>
                                    )
                                </argument_list>
                            </call>
                        </expr>
                        ;
                    </expr_stmt>
                    <expr_stmt>
                        <expr>
                            <call>
                                <name><name>expected</name>.
                                    <name>add</name>
                                </name>
                                <argument_list>(
                                    <argument>
                                        <expr>new
                                            <call>
                                                <name>LogRecord</name>
                                                <argument_list>(
                                                    <argument>
                                                        <expr>
                                                            <name><name>SimpleLog</name>.
                                                                <name>LOG_LEVEL_FATAL</name>
                                                            </name>
                                                        </expr>
                                                    </argument>
                                                    ,
                                                    <argument>
                                                        <expr>"fatal"</expr>
                                                    </argument>
                                                    ,
                                                    <argument>
                                                        <expr>
                                                            <name>null</name>
                                                        </expr>
                                                    </argument>
                                                    )
                                                </argument_list>
                                            </call>
                                        </expr>
                                    </argument>
                                    )
                                </argument_list>
                            </call>
                        </expr>
                        ;
                    </expr_stmt>

                    }
                </block>
            </function>


            }
        </block>
    </class>
</unit>
